Workbook

Sheet instrument_translations_templat
A1: instrument_en | B1: instrument_zh | C1: description
A2: 16PF
A3: 6FPQ
A4: 7FACTOR
A5: AB5C
A6: Barchard2001
A7: BFAS
A8: BFAS-20
A9: BIDR
A10: BIS_BAS
A11: Buss1980
A12: Cacioppo1982
A13: CAT-PD
... A37: VIA

Sheet label_translations_template
A1: label_en | B1: label_zh | C1: description
A2: Achievement-striving | B2: 成就追求
A3: Activity-Level | B3: 活動水平
A4: Adaptability | B4: 適應性
A5: ADHD | B5: ADHD
A6: Adventurousness | B6: 冒險性
A7: Aesthetic Appreciation/Artistic Interests | B7: 美學欣賞/藝術興趣
A8: Affective Lability | B8: 情感不穩定
A9: Agreeableness | B9: 親和性
A10: Altruism | B10: 利他主義
A11: Ambition/Drive | B11: 野心/動力
A12: Amiability | B12: 和藹
A13: Anger | B13: 憤怒
... A139: Locus of Control | B139: 控制源
A140: Locus of Control | B140: Chance | C140: 控制源 | D140: 機會
A141: Locus of Control | B141: External | C141: 控制源 | D141: 外在
A142: Locus of Control | B142: Internal | C142: 控制源 | D142: 內在
A143: Locus of Control | B143: Rational | C143: 控制源 | D143: 理性
A144: Love of Learning | B144: 學習熱愛
A145: Love of Reading | B145: 閱讀熱愛
A146: Machiavellianism | B146: 權謀主義
A147: Manipulativeness | B147: 操縱性
A148: Methodicalness | B148: 條理性
A149: Mistrust | B149: 不信任
A150: Moderation | B150: 節制
A151: Modesty/Humility | B151: 謙虛/謙遜
A152: Morality | B152: 道德性
A153: Need for Cognition | B153: 認知需求
A154: Need for Order and Cleanliness | B154: 對秩序和清潔的需求
A155: Negative Expressivity | B155: 負向表達性
... A247: Workaholism | B247: 工作狂

Sheet IPIP_items-merged
A1: instrument | B1: alpha | C1: alpha2 | D1: scoring_key | E1: text_en | F1: text_zh | G1: label | H1: label_zh | I1: IPIP_item_number
A2: 16PF | B2: 0.78 | D2: 1 | E2: Act wild and crazy. | F2: 行為狂野瘋狂。 | G2: Gregariousness | H2: 合群性 | I2: =_xlfn.XLOOKUP(E2,IPIP3320!A:A,IPIP3320!B:B,"") -> H871
A3: 16PF | B3: 0.8 | D3: 1 | E3: Am afraid that I will do the wrong thing. | F3: 我擔心自己會做錯事。 | G3: Anxiety | H3: 焦慮 | I3: =_xlfn.XLOOKUP(E3,IPIP3320!A:A,IPIP3320!B:B,"") -> H905
A4: 16PF | B4: 0.76 | D4: 1 | E4: Am annoyed by others' mistakes. | F4: 我會因他人的錯誤而感到煩躁。 | G4: Emotionality | H4: 情緒性 | I4: =_xlfn.XLOOKUP(E4,IPIP3320!A:A,IPIP3320!B:B,"") -> E82
A5: 16PF | B5: 0.85 | D5: -1 | E5: Am easily discouraged. | F5: 我容易感到沮喪。 | G5: Emotional Stability | H5: 情緒穩定性 | I5: =_xlfn.XLOOKUP(E5,IPIP3320!A:A,IPIP3320!B:B,"") -> H647
A6: 16PF | B6: 0.8 | D6: 1 | E6: Am easily hurt. | F6: 我容易受傷。 | G6: Anxiety | H6: 焦慮 | I6: =_xlfn.XLOOKUP(E6,IPIP3320!A:A,IPIP3320!B:B,"") -> H987
A7: 16PF | B7: 0.76 | D7: 1 | E7: Am easily put out. | F7: 我容易生氣。 | G7: Emotionality | H7: 情緒性 | I7: =_xlfn.XLOOKUP(E7,IPIP3320!A:A,IPIP3320!B:B,"") -> H641
A8: 16PF | B8: 0.81 | D8: 1 | E8: Am exacting in my work. | F8: 我對工作要求嚴格。 | G8: Orderliness | H8: 條理性 | I8: =_xlfn.XLOOKUP(E8,IPIP3320!A:A,IPIP3320!B:B,"") -> X163
A9: 16PF | B9: 0.86 | D9: 1 | E9: Am hard to get to know. | F9: 我很難被了解。 | G9: Reserve | H9: 保守性 | I9: =_xlfn.XLOOKUP(E9,IPIP3320!A:A,IPIP3320!B:B,"") -> H596, X9
A10: 16PF | B10: 0.81 | D10: 1 | E10: Am not afraid of providing criticism. | F10: 我不怕提出批評。 | G10: Dominance | H10: 支配性 | I10: =_xlfn.XLOOKUP(E10,IPIP3320!A:A,IPIP3320!B:B,"") -> H459
A11: 16PF | B11: 0.81 | D11: 1 | E11: Am not afraid of providing criticism. | F11: 我不怕提出批評。 | G11: Assertiveness | H11: 自信堅定 | I11: =_xlfn.XLOOKUP(E11,IPIP3320!A:A,IPIP3320!B:B,"") -> H459
A12: 16PF | B12: 0.81 | D12: -1 | E12: Am not bothered by disorder. | F12: 我不會被混亂所困擾。 | G12: Orderliness | H12: 條理性 | I12: =_xlfn.XLOOKUP(E12,IPIP3320!A:A,IPIP3320!B:B,"") -> E7
A13: 16PF | B13: 0.81 | D13: -1 | E13: Am not bothered by messy people. | F13: 我不會被凌亂的人困擾。 | G13: Orderliness | H13: 條理性 | I13: =_xlfn.XLOOKUP(E13,IPIP3320!A:A,IPIP3320!B:B,"") -> E100
... A920: AB5C | B920: 0.71 | D920: 1 | E920: Wouldn't harm a fly. | F920: 我不會傷害一隻蒼蠅。 | G920: Nurturance | H920: 培育 | I920: =_xlfn.XLOOKUP(E920,IPIP3320!A:A,IPIP3320!B:B,"") -> H142
A921: Barchard2001 | B921: 0.59 | C921: 0.63 | D921: -1 | E921: Am calm even in tense situations. | F921: 即使在緊張的情況下我也很冷靜。 | G921: Responsive Distress | H921: 反應性苦惱 | I921: =_xlfn.XLOOKUP(E921,IPIP3320!A:A,IPIP3320!B:B,"") -> E64
A922: Barchard2001 | B922: 0.64 | C922: 0.8 | D922: 1 | E922: Am concerned about others. | F922: 我關心他人。 | G922: Empathy | H922: 同理心 | I922: =_xlfn.XLOOKUP(E922,IPIP3320!A:A,IPIP3320!B:B,"") -> H1100, X31
A923: Barchard2001 | B923: 0.59 | C923: 0.63 | D923: 1 | E923: Am deeply moved by others' misfortunes. | F923: 我深受他人的不幸所感動。 | G923: Responsive Distress | H923: 反應性苦惱 | I923: =_xlfn.XLOOKUP(E923,IPIP3320!A:A,IPIP3320!B:B,"") -> X253
A924: Barchard2001 | B924: 0.59 | C924: 0.63 | D924: 1 | E924: Am easily moved to tears. | F924: 我容易被感動而流淚。 | G924: Responsive Distress | H924: 反應性苦惱 | I924: =_xlfn.XLOOKUP(E924,IPIP3320!A:A,IPIP3320!B:B,"") -> H992
A925: Barchard2001 | B925: 0.59 | C925: 0.63 | D925: -1 | E925: Am not easily disturbed by events. | F925: 我不容易被事件所困擾。 | G925: Responsive Distress | H925: 反應性苦惱 | I925: =_xlfn.XLOOKUP(E925,IPIP3320!A:A,IPIP3320!B:B,"") -> H1046, X11
A926: Barchard2001 | B926: 0.81 | C926: 0.83 | D926: -1 | E926: Am not in touch with my feelings. | F926: 我與自己的感受脫節。 | G926: Attention to Emotions | H926: 情緒關注 | I926: =_xlfn.XLOOKUP(E926,IPIP3320!A:A,IPIP3320!B:B,"") -> E9
A927: Barchard2001 | B927: 0.73 | C927: 0.7 | D927: 1 | E927: Am strongly influenced by the good moods of others. | F927: 我受到他人良好情緒的強烈影響。 | G927: Responsive Joy | H927: 反應性喜悅 | I927: =_xlfn.XLOOKUP(E927,IPIP3320!A:A,IPIP3320!B:B,"") -> A72
A928: Barchard2001 | B928: 0.73 | C928: 0.7 | D928: -1 | E928: Am unaffected by other people's happiness. | F928: 我不受他人幸福的影響。 | G928: Responsive Joy | H928: 反應性喜悅 | I928: =_xlfn.XLOOKUP(E928,IPIP3320!A:A,IPIP3320!B:B,"") -> A11
A929: Barchard2001 | B929: 0.59 | C929: 0.63 | D929: -1 | E929: Am unaffected by the suffering of others. | F929: 我不受他人痛苦的影響。 | G929: Responsive Distress | H929: 反應性苦惱 | I929: =_xlfn.XLOOKUP(E929,IPIP3320!A:A,IPIP3320!B:B,"") -> A67
A930: Barchard2001 | B930: 0.59 | C930: 0.63 | D930: 1 | E930: Am upset by the misfortunes of strangers. | F930: 我為陌生人的不幸感到難過。 | G930: Responsive Distress | H930: 反應性苦惱 | I930: =_xlfn.XLOOKUP(E930,IPIP3320!A:A,IPIP3320!B:B,"") -> A135
A931: Barchard2001 | B931: 0.81 | C931: 0.83 | D931: 1 | E931: Am usually aware of the way that I'm feeling. | F931: 我通常意識到自己的感受。 | G931: Attention to Emotions | H931: 情緒關注 | I931: =_xlfn.XLOOKUP(E931,IPIP3320!A:A,IPIP3320!B:B,"") -> A122
A932: Barchard2001 | B932: 0.73 | C932: 0.67 | D932: 1 | E932: Base my goals in life on inspiration, rather than logic. | F932: 我的人生目標基於啟發而非邏輯。 | G932: Emotion-based Decision-making | H932: 基於情緒的決策 | I932: =_xlfn.XLOOKUP(E932,IPIP3320!A:A,IPIP3320!B:B,"") -> A26
... A988: Barchard2001 | B988: 0.59 | C988: 0.63 | D988: 1 | E988: Would be upset if I saw an injured animal. | F988: 如果我看到受傷的動物，我會感到難過。 | G988: Responsive Distress | H988: 反應性苦惱 | I988: =_xlfn.XLOOKUP(E988,IPIP3320!A:A,IPIP3320!B:B,"") -> A46
A989: BFAS | B989: 0.81 | D989: 1 | E989: Always know what I am doing. | F989: 我總是知道自己在做什麼。 | G989: Industriousness/Perseverance/Persistence | H989: 勤勉/堅持/毅力 | I989: =_xlfn.XLOOKUP(E989,IPIP3320!A:A,IPIP3320!B:B,"") -> P427
A990: BFAS | B990: 0.89 | D990: 1 | E990: Am a person whose moods go up and down easily. | F990: 我是個情緒起伏的人。 | G990: Neuroticism | H990: 神經質 | I990: =_xlfn.XLOOKUP(E990,IPIP3320!A:A,IPIP3320!B:B,"")
A991: BFAS | B991: 0.89 | D991: 1 | E991: Am a person whose moods go up and down easily. | F991: 我是個情緒起伏的人。 | G991: Anger | H991: 憤怒 | I991: =_xlfn.XLOOKUP(E991,IPIP3320!A:A,IPIP3320!B:B,"")
A992: BFAS | B992: 0.89 | D992: 1 | E992: Am afraid of many things. | F992: 我害怕很多事情。 | G992: Neuroticism | H992: 神經質 | I992: =_xlfn.XLOOKUP(E992,IPIP3320!A:A,IPIP3320!B:B,"") -> H968
A993: BFAS | B993: 0.84 | D993: 1 | E993: Am afraid of many things. | F993: 我害怕很多事情。 | G993: Anxiety | H993: 焦慮 | I993: =_xlfn.XLOOKUP(E993,IPIP3320!A:A,IPIP3320!B:B,"") -> H968
A994: BFAS | B994: 0.89 | D994: 1 | E994: Am easily discouraged. | F994: 我容易感到沮喪。 | G994: Neuroticism | H994: 神經質 | I994: =_xlfn.XLOOKUP(E994,IPIP3320!A:A,IPIP3320!B:B,"") -> H647
A995: BFAS | B995: 0.84 | D995: 1 | E995: Am easily discouraged. | F995: 我容易感到沮喪。 | G995: Anxiety | H995: 焦慮 | I995: =_xlfn.XLOOKUP(E995,IPIP3320!A:A,IPIP3320!B:B,"") -> H647
A996: BFAS | B996: 0.81 | D996: -1 | E996: Am easily distracted. | F996: 我容易分心。 | G996: Industriousness/Perseverance/Persistence | H996: 勤勉/堅持/毅力 | I996: =_xlfn.XLOOKUP(E996,IPIP3320!A:A,IPIP3320!B:B,"") -> H843, F44, T192
A997: BFAS | B997: 0.89 | D997: 1 | E997: Am filled with doubts about things. | F997: 我對事情充滿疑慮。 | G997: Neuroticism | H997: 神經質 | I997: =_xlfn.XLOOKUP(E997,IPIP3320!A:A,IPIP3320!B:B,"") -> H683
A998: BFAS | B998: 0.84 | D998: 1 | E998: Am filled with doubts about things. | F998: 我對事情充滿疑慮。 | G998: Anxiety | H998: 焦慮 | I998: =_xlfn.XLOOKUP(E998,IPIP3320!A:A,IPIP3320!B:B,"") -> H683
A999: BFAS | B999: 0.81 | D999: -1 | E999: Am hard to get to know. | F999: 我很難被了解。 | G999: Vitality/Enthusiasm/Zest | H999: 活力/熱情/熱忱 | I999: =_xlfn.XLOOKUP(E999,IPIP3320!A:A,IPIP3320!B:B,"") -> H596, X9
A1000: BFAS | B1000: 0.84 | D1000: -1 | E1000: Am indifferent to the feelings of others. | F1000: 我對他人的感受漠不關心。 | G1000: Compassion | H1000: 同情心 | I1000: =_xlfn.XLOOKUP(E1000,IPIP3320!A:A,IPIP3320!B:B,"") -> X203
... A1217: BIDR | B1217: 0.87 | D1217: 1 | E1217: Would never take things that aren't mine. | F1217: 我永遠不會拿不屬於我的東西。 | G1217: Impression-Management | H1217: 印象管理 | I1217: =_xlfn.XLOOKUP(E1217,IPIP3320!A:A,IPIP3320!B:B,"") -> P367
A1218: BIS_BAS | D1218: 1 | E1218: Am afraid that I will do the wrong thing. | F1218: 我擔心自己會做錯事。 | G1218: Behavioral Inhibition/Activation System | H1218: 行為抑制/激活系統 | I1218: =_xlfn.XLOOKUP(E1218,IPIP3320!A:A,IPIP3320!B:B,"") -> H905
A1219: BIS_BAS | D1219: 1 | E1219: Am always worried about something. | F1219: 我總是擔心某事。 | G1219: Behavioral Inhibition/Activation System | H1219: 行為抑制/激活系統 | I1219: =_xlfn.XLOOKUP(E1219,IPIP3320!A:A,IPIP3320!B:B,"") -> D96
A1220: BIS_BAS | D1220: 1 | E1220: Am always worried about something. | F1220: 我總是擔心某事。 | G1220: Anxiety | H1220: 焦慮 | I1220: =_xlfn.XLOOKUP(E1220,IPIP3320!A:A,IPIP3320!B:B,"") -> D96
A1221: BIS_BAS | B1221: 0.68 | D1221: 1 | E1221: Am eager to soothe hurt feelings. | F1221: 我渴望撫慰受傷的感受。 | G1221: Excitement-seeking | H1221: 尋求刺激 | I1221: =_xlfn.XLOOKUP(E1221,IPIP3320!A:A,IPIP3320!B:B,"") -> Q117
A1222: BIS_BAS | D1222: 1 | E1222: Am easily hurt. | F1222: 我容易受傷。 | G1222: Behavioral Inhibition/Activation System | H1222: 行為抑制/激活系統 | I1222: =_xlfn.XLOOKUP(E1222,IPIP3320!A:A,IPIP3320!B:B,"") -> H987
A1223: BIS_BAS | B1223: 0.77 | D1223: -1 | E1223: Am not an extraordinary person. | F1223: 我不是個非凡的人。 | G1223: Ambition/Drive | H1223: 野心/動力 | I1223: =_xlfn.XLOOKUP(E1223,IPIP3320!A:A,IPIP3320!B:B,"") -> P462
A1224: BIS_BAS | D1224: -1 | E1224: Am not embarrassed easily. | F1224: 我不容易感到尷尬。 | G1224: Behavioral Inhibition/Activation System | H1224: 行為抑制/激活系統 | I1224: =_xlfn.XLOOKUP(E1224,IPIP3320!A:A,IPIP3320!B:B,"") -> X242
A1225: BIS_BAS | B1225: 0.77 | D1225: -1 | E1225: Am not highly motivated to succeed. | F1225: 我沒有強烈的成功動機。 | G1225: Ambition/Drive | H1225: 野心/動力 | I1225: =_xlfn.XLOOKUP(E1225,IPIP3320!A:A,IPIP3320!B:B,"") -> X110
A1226: BIS_BAS | B1226: 0.79 | D1226: 1 | E1226: Am willing to try anything once. | F1226: 我願意嘗試任何事。 | G1226: Risk-taking/Sensation-Seeking/Thrill-Seeking | H1226: 冒險/尋求感覺/尋求刺激 | I1226: =_xlfn.XLOOKUP(E1226,IPIP3320!A:A,IPIP3320!B:B,"") -> X3
A1227: BIS_BAS | B1227: 0.79 | D1227: -1 | E1227: Avoid dangerous situations. | F1227: 我避免危險情況。 | G1227: Risk-taking/Sensation-Seeking/Thrill-Seeking | H1227: 冒險/尋求感覺/尋求刺激 | I1227: =_xlfn.XLOOKUP(E1227,IPIP3320!A:A,IPIP3320!B:B,"") -> H317
A1228: BIS_BAS | D1228: 1 | E1228: Become overwhelmed by events. | F1228: 我被事件壓倒。 | G1228: Behavioral Inhibition/Activation System | H1228: 行為抑制/激活系統 | I1228: =_xlfn.XLOOKUP(E1228,IPIP3320!A:A,IPIP3320!B:B,"") -> H959
A1229: BIS_BAS | D1229: 1 | E1229: Begin to panic when there is danger. | F1229: 當有危險時我開始驚慌。 | G1229: Behavioral Inhibition/Activation System | H1229: 行為抑制/激活系統 | I1229: =_xlfn.XLOOKUP(E1229,IPIP3320!A:A,IPIP3320!B:B,"") -> Q50
A1230: BIS_BAS | D1230: 1 | E1230: Begin to panic when there is danger. | F1230: 當有危險時我開始驚慌。 | G1230: Anxiety | H1230: 焦慮 | I1230: =_xlfn.XLOOKUP(E1230,IPIP3320!A:A,IPIP3320!B:B,"") -> Q50
A1231: BIS_BAS | B1231: 0.79 | D1231: 1 | E1231: Do crazy things. | F1231: 我做瘋狂的事情。 | G1231: Risk-taking/Sensation-Seeking/Thrill-Seeking | H1231: 冒險/尋求感覺/尋求刺激 | I1231: =_xlfn.XLOOKUP(E1231,IPIP3320!A:A,IPIP3320!B:B,"") -> H870
A1232: BIS_BAS | B1232: 0.68 | D1232: -1 | E1232: Don't get excited about things. | F1232: 我對事物不感到興奮。 | G1232: Excitement-seeking | H1232: 尋求刺激 | I1232: =_xlfn.XLOOKUP(E1232,IPIP3320!A:A,IPIP3320!B:B,"") -> H572
A1233: BIS_BAS | B1233: 0.79 | D1233: 1 | E1233: Enjoy being reckless. | F1233: 我喜歡冒險行事。 | G1233: Risk-taking/Sensation-Seeking/Thrill-Seeking | H1233: 冒險/尋求感覺/尋求刺激 | I1233: =_xlfn.XLOOKUP(E1233,IPIP3320!A:A,IPIP3320!B:B,"") -> E35
A1234: BIS_BAS | B1234: 0.68 | D1234: 1 | E1234: Feel excited or happy for no apparent reason. | F1234: 我無緣無故感到興奮或快樂。 | G1234: Excitement-seeking | H1234: 尋求刺激 | I1234: =_xlfn.XLOOKUP(E1234,IPIP3320!A:A,IPIP3320!B:B,"") -> R33
A1235: BIS_BAS | B1235: 0.68 | D1235: 1 | E1235: Get caught up in the excitement when others are celebrating. | F1235: 當他人慶祝時，我會被興奮感染。 | G1235: Excitement-seeking | H1235: 尋求刺激 | I1235: =_xlfn.XLOOKUP(E1235,IPIP3320!A:A,IPIP3320!B:B,"") -> A71
A1236: BIS_BAS | B1236: 0.68 | D1236: 1 | E1236: Get so happy or energetic that I am almost giddy. | F1236: 我變得如此快樂或精力充沛，幾乎有點頭暈。 | G1236: Excitement-seeking | H1236: 尋求刺激 | I1236: =_xlfn.XLOOKUP(E1236,IPIP3320!A:A,IPIP3320!B:B,"") -> R43
A1237: BIS_BAS | D1237: 1 | E1237: Get stressed out easily. | F1237: 我容易感到壓力。 | G1237: Behavioral Inhibition/Activation System | H1237: 行為抑制/激活系統 | I1237: =_xlfn.XLOOKUP(E1237,IPIP3320!A:A,IPIP3320!B:B,"") -> X107
A1238: BIS_BAS | D1238: 1 | E1238: Get stressed out easily. | F1238: 我容易感到壓力。 | G1238: Anxiety | H1238: 焦慮 | I1238: =_xlfn.XLOOKUP(E1238,IPIP3320!A:A,IPIP3320!B:B,"") -> X107
A1239: BIS_BAS | B1239: 0.77 | D1239: -1 | E1239: Hate being the center of attention. | F1239: 我討厭成為注意力的焦點。 | G1239: Ambition/Drive | H1239: 野心/動力 | I1239: =_xlfn.XLOOKUP(E1239,IPIP3320!A:A,IPIP3320!B:B,"") -> P434
A1240: BIS_BAS | B1240: 0.77 | D1240: 1 | E1240: Have a strong need for power. | F1240: 我有強烈的權力需求。 | G1240: Ambition/Drive | H1240: 野心/動力 | I1240: =_xlfn.XLOOKUP(E1240,IPIP3320!A:A,IPIP3320!B:B,"") -> P445
A1241: BIS_BAS | B1241: 0.79 | D1241: 1 | E1241: Have persuaded others to do something really adventurous or crazy. | F1241: 我說服他人做真正冒險或瘋狂的事。 | G1241: Risk-taking/Sensation-Seeking/Thrill-Seeking | H1241: 冒險/尋求感覺/尋求刺激 | I1241: =_xlfn.XLOOKUP(E1241,IPIP3320!A:A,IPIP3320!B:B,"") -> R58
A1242: BIS_BAS | B1242: 0.77 | D1242: 1 | E1242: Know how to get around the rules. | F1242: 我知道如何規避規則。 | G1242: Ambition/Drive | H1242: 野心/動力 | I1242: =_xlfn.XLOOKUP(E1242,IPIP3320!A:A,IPIP3320!B:B,"") -> H1327
A1243: BIS_BAS | B1243: 0.79 | D1243: 1 | E1243: Like to act on a whim. | F1243: 我喜歡憑一時衝動行事。 | G1243: Risk-taking/Sensation-Seeking/Thrill-Seeking | H1243: 冒險/尋求感覺/尋求刺激 | I1243: =_xlfn.XLOOKUP(E1243,IPIP3320!A:A,IPIP3320!B:B,"") -> E122
A1244: BIS_BAS | B1244: 0.79 | D1244: 1 | E1244: Like to behave spontaneously. | F1244: 我喜歡自發地行為。 | G1244: Risk-taking/Sensation-Seeking/Thrill-Seeking | H1244: 冒險/尋求感覺/尋求刺激 | I1244: =_xlfn.XLOOKUP(E1244,IPIP3320!A:A,IPIP3320!B:B,"") -> D58
A1245: BIS_BAS | B1245: 0.77 | D1245: 1 | E1245: Like to show off my body. | F1245: 我喜歡炫耀我的身體。 | G1245: Ambition/Drive | H1245: 野心/動力 | I1245: =_xlfn.XLOOKUP(E1245,IPIP3320!A:A,IPIP3320!B:B,"") -> P474
A1246: BIS_BAS | D1246: 1 | E1246: Often worry about things that turn out to be unimportant. | F1246: 我經常擔心事後證明不重要的事情。 | G1246: Behavioral Inhibition/Activation System | H1246: 行為抑制/激活系統 | I1246: =_xlfn.XLOOKUP(E1246,IPIP3320!A:A,IPIP3320!B:B,"") -> D71
A1247: BIS_BAS | D1247: 1 | E1247: Often worry about things that turn out to be unimportant. | F1247: 我經常擔心事後證明不重要的事情。 | G1247: Anxiety | H1247: 焦慮 | I1247: =_xlfn.XLOOKUP(E1247,IPIP3320!A:A,IPIP3320!B:B,"") -> D71
A1248: BIS_BAS | B1248: 0.79 | D1248: 1 | E1248: Prefer friends who are excitingly unpredictable. | F1248: 我喜歡令人興奮且不可預測的朋友。 | G1248: Risk-taking/Sensation-Seeking/Thrill-Seeking | H1248: 冒險/尋求感覺/尋求刺激 | I1248: =_xlfn.XLOOKUP(E1248,IPIP3320!A:A,IPIP3320!B:B,"") -> R5
A1249: BIS_BAS | B1249: 0.77 | D1249: 1 | E1249: Push myself very hard to succeed. | F1249: 我非常努力地推動自己成功。 | G1249: Ambition/Drive | H1249: 野心/動力 | I1249: =_xlfn.XLOOKUP(E1249,IPIP3320!A:A,IPIP3320!B:B,"") -> Q204
A1250: BIS_BAS | B1250: 0.79 | D1250: -1 | E1250: Rarely enjoy behaving in a silly manner. | F1250: 我很少享受以愚蠢的方式行為。 | G1250: Risk-taking/Sensation-Seeking/Thrill-Seeking | H1250: 冒險/尋求感覺/尋求刺激 | I1250: =_xlfn.XLOOKUP(E1250,IPIP3320!A:A,IPIP3320!B:B,"") -> D75
A1251: BIS_BAS | B1251: 0.68 | D1251: -1 | E1251: Rarely get caught up in the excitement. | F1251: 我很少被興奮感染。 | G1251: Excitement-seeking | H1251: 尋求刺激 | I1251: =_xlfn.XLOOKUP(E1251,IPIP3320!A:A,IPIP3320!B:B,"") -> A13
A1252: BIS_BAS | D1252: -1 | E1252: Rarely worry. | F1252: 我很少擔心。 | G1252: Behavioral Inhibition/Activation System | H1252: 行為抑制/激活系統 | I1252: =_xlfn.XLOOKUP(E1252,IPIP3320!A:A,IPIP3320!B:B,"") -> D79
A1253: BIS_BAS | D1253: -1 | E1253: Rarely worry. | F1253: 我很少擔心。 | G1253: Anxiety | H1253: 焦慮 | I1253: =_xlfn.XLOOKUP(E1253,IPIP3320!A:A,IPIP3320!B:B,"") -> D79
A1254: BIS_BAS | B1254: 0.77 | D1254: 1 | E1254: Take charge. | F1254: 我會掌控。 | G1254: Ambition/Drive | H1254: 野心/動力 | I1254: =_xlfn.XLOOKUP(E1254,IPIP3320!A:A,IPIP3320!B:B,"") -> H334, X27
A1255: BIS_BAS | B1255: 0.77 | D1255: 1 | E1255: Try to surpass others' accomplishments. | F1255: 我試圖超越他人的成就。 | G1255: Ambition/Drive | H1255: 野心/動力 | I1255: =_xlfn.XLOOKUP(E1255,IPIP3320!A:A,IPIP3320!B:B,"") -> H1193
A1256: BIS_BAS | B1256: 0.77 | D1256: 1 | E1256: Want to be in charge. | F1256: 我想要掌控。 | G1256: Ambition/Drive | H1256: 野心/動力 | I1256: =_xlfn.XLOOKUP(E1256,IPIP3320!A:A,IPIP3320!B:B,"") -> H793
A1257: BIS_BAS | D1257: 1 | E1257: Worry about what people think of me. | F1257: 我擔心人們對我的看法。 | G1257: Behavioral Inhibition/Activation System | H1257: 行為抑制/激活系統 | I1257: =_xlfn.XLOOKUP(E1257,IPIP3320!A:A,IPIP3320!B:B,"") -> P420
A1258: BIS_BAS | D1258: 1 | E1258: Worry about what people think of me. | F1258: 我擔心人們對我的看法。 | G1258: Anxiety | H1258: 焦慮 | I1258: =_xlfn.XLOOKUP(E1258,IPIP3320!A:A,IPIP3320!B:B,"") -> P420
A1259: BIS_BAS | B1259: 0.79 | D1259: -1 | E1259: Would never go hang gliding or bungee jumping. | F1259: 我永遠不會去滑翔傘或高空彈跳。 | G1259: Risk-taking/Sensation-Seeking/Thrill-Seeking | H1259: 冒險/尋求感覺/尋求刺激 | I1259: =_xlfn.XLOOKUP(E1259,IPIP3320!A:A,IPIP3320!B:B,"")
A1260: Buss1980 | B1260: 0.81 | D1260: 1 | E1260: Am constantly reflecting about myself. | F1260: 我不斷反思自己。 | G1260: Introspection/Private Self-Consciousness | H1260: 內省/私人自我意識 | I1260: =_xlfn.XLOOKUP(E1260,IPIP3320!A:A,IPIP3320!B:B,"") -> P395
A1261: Buss1980 | B1261: 0.77 | D1261: 1 | E1261: Am easily intimidated. | F1261: 我容易被威脅。 | G1261: Public Self-consciousness | H1261: 公眾自我意識 | I1261: =_xlfn.XLOOKUP(E1261,IPIP3320!A:A,IPIP3320!B:B,"") -> H991, X41
A1262: Buss1980 | B1262: 0.77 | D1262: -1 | E1262: Am not concerned with making a good impression. | F1262: 我不在意給人留下好印象。 | G1262: Public Self-consciousness | H1262: 公眾自我意識 | I1262: =_xlfn.XLOOKUP(E1262,IPIP3320!A:A,IPIP3320!B:B,"") -> P397
A1263: Buss1980 | B1263: 0.77 | D1263: -1 | E1263: Am not easily bothered by things. | F1263: 我不容易被事情困擾。 | G1263: Public Self-consciousness | H1263: 公眾自我意識 | I1263: =_xlfn.XLOOKUP(E1263,IPIP3320!A:A,IPIP3320!B:B,"") -> X138
A1264: Buss1980 | B1264: 0.77 | D1264: -1 | E1264: Am not embarrassed easily. | F1264: 我不容易感到尷尬。 | G1264: Public Self-consciousness | H1264: 公眾自我意識 | I1264: =_xlfn.XLOOKUP(E1264,IPIP3320!A:A,IPIP3320!B:B,"") -> X242
A1265: Buss1980 | B1265: 0.81 | D1265: -1 | E1265: Don't try to figure myself out. | F1265: 我不試圖弄清楚自己。 | G1265: Introspection/Private Self-Consciousness | H1265: 內省/私人自我意識 | I1265: =_xlfn.XLOOKUP(E1265,IPIP3320!A:A,IPIP3320!B:B,"") -> P363
A1266: Buss1980 | B1266: 0.77 | D1266: -1 | E1266: Don't worry about things that have already happened. | F1266: 我不擔心已經發生的事情。 | G1266: Public Self-consciousness | H1266: 公眾自我意識 | I1266: =_xlfn.XLOOKUP(E1266,IPIP3320!A:A,IPIP3320!B:B,"") -> E150
A1267: Buss1980 | B1267: 0.81 | D1267: 1 | E1267: Examine my motives constantly. | F1267: 我不斷審查自己的動機。 | G1267: Introspection/Private Self-Consciousness | H1267: 內省/私人自我意識 | I1267: =_xlfn.XLOOKUP(E1267,IPIP3320!A:A,IPIP3320!B:B,"") -> P377
A1268: Buss1980 | B1268: 0.77 | D1268: -1 | E1268: Feel comortable with myself. | F1268: 我對自己感到自在。 | G1268: Public Self-consciousness | H1268: 公眾自我意識 | I1268: =_xlfn.XLOOKUP(E1268,IPIP3320!A:A,IPIP3320!B:B,"")
A1269: Buss1980 | B1269: 0.77 | D1269: 1 | E1269: Feel threatened easily. | F1269: 我容易感到威脅。 | G1269: Public Self-consciousness | H1269: 公眾自我意識 | I1269: =_xlfn.XLOOKUP(E1269,IPIP3320!A:A,IPIP3320!B:B,"") -> H612
A1270: Buss1980 | B1270: 0.81 | D1270: 1 | E1270: Like to get lost in thought. | F1270: 我喜歡陷入沉思。 | G1270: Introspection/Private Self-Consciousness | H1270: 內省/私人自我意識 | I1270: =_xlfn.XLOOKUP(E1270,IPIP3320!A:A,IPIP3320!B:B,"") -> E163
... A1290: Cacioppo1982 | B1290: 0.93 | D1290: -1 | E1290: Try to avoid complex people. | F1290: 我試圖避開複雜的人。 | G1290: Need for Cognition | H1290: 認知需求 | I1290: =_xlfn.XLOOKUP(E1290,IPIP3320!A:A,IPIP3320!B:B,"") -> E171
A1291: CAT-PD | B1291: 0.82 | C1291: 0.84 | D1291: 1 | E1291: Act without planning. | F1291: 我不做計劃就行動。 | G1291: Non-Planfulness | H1291: 非計劃性 | I1291: =_xlfn.XLOOKUP(E1291,IPIP3320!A:A,IPIP3320!B:B,"") -> H848
A1292: CAT-PD | B1292: 0.85 | C1292: 0.83 | D1292: 1 | E1292: Am a cold-hearted person. | F1292: 我是個冷酷無情的人。 | G1292: Callousness | H1292: 冷漠 | I1292: =_xlfn.XLOOKUP(E1292,IPIP3320!A:A,IPIP3320!B:B,"") -> T63
A1293: CAT-PD | B1293: 0.82 | C1293: 0.84 | D1293: -1 | E1293: Am a firm believer in thinking things through. | F1293: 我堅信要深思熟慮。 | G1293: Non-Planfulness | H1293: 非計劃性 | I1293: =_xlfn.XLOOKUP(E1293,IPIP3320!A:A,IPIP3320!B:B,"")
A1294: CAT-PD | B1294: 0.83 | C1294: 0.84 | D1294: -1 | E1294: Am a law-abiding citizen. | F1294: 我是個守法的公民。 | G1294: Norm Violation | H1294: 違反規範 | I1294: =_xlfn.XLOOKUP(E1294,IPIP3320!A:A,IPIP3320!B:B,"") -> T81
A1295: CAT-PD | B1295: 0.86 | C1295: 0.82 | D1295: 1 | E1295: Am a strange person. | F1295: 我是個奇怪的人。 | G1295: Peculiarity | H1295: 怪異 | I1295: =_xlfn.XLOOKUP(E1295,IPIP3320!A:A,IPIP3320!B:B,"") -> T99
A1296: CAT-PD | B1296: 0.82 | C1296: 0.85 | D1296: -1 | E1296: Am a very reliable person. | F1296: 我是個非常可靠的人。 | G1296: Irresponsibility | H1296: 不負責任 | I1296: =_xlfn.XLOOKUP(E1296,IPIP3320!A:A,IPIP3320!B:B,"") -> T103
...

Sheet IPIP_items
A1: instrument | B1: alpha | C1: key | D1: text | E1: label
A2: 16PF | B2: 0.78 | C2: 1 | D2: Act wild and crazy. | E2: Gregariousness
A3: 16PF | B3: 0.8 | C3: 1 | D3: Am afraid that I will do the wrong thing. | E3: Anxiety
A4: 16PF | B4: 0.76 | C4: 1 | D4: Am annoyed by others' mistakes. | E4: Emotionality
A5: 16PF | B5: 0.85 | C5: -1 | D5: Am easily discouraged. | E5: Emotional Stability
A6: 16PF | B6: 0.8 | C6: 1 | D6: Am easily hurt. | E6: Anxiety
A7: 16PF | B7: 0.76 | C7: 1 | D7: Am easily put out. | E7: Emotionality
A8: 16PF | B8: 0.81 | C8: 1 | D8: Am exacting in my work. | E8: Orderliness
A9: 16PF | B9: 0.86 | C9: 1 | D9: Am hard to get to know. | E9: Reserve
A10: 16PF | B10: 0.81 | C10: 1 | D10: Am not afraid of providing criticism. | E10: Dominance
A11: 16PF | B11: 0.81 | C11: 1 | D11: Am not afraid of providing criticism. | E11: Assertiveness
A12: 16PF | B12: 0.81 | C12: -1 | D12: Am not bothered by disorder. | E12: Orderliness
... A2439: HPI-HIC | B2439: 0.81 | C2439: -1 | D2439: Yell at people. | E2439: Cool-headedness
A2440: IPIP-IPC | C2440: 1 | D2440: Am a very private person | E2440: Introversion
A2441: IPIP-IPC | C2441: 1 | D2441: Am interested in people | E2441: Warmth
A2442: IPIP-IPC | C2442: 1 | D2442: Am not interested in other people��s problems. | E2442: Callousness
A2443: IPIP-IPC | C2443: 1 | D2443: Am quiet around strangers | E2443: Introversion
A2444: IPIP-IPC | C2444: 1 | D2444: Believe people should fend for themselves. | E2444: Callousness
A2445: IPIP-IPC | C2445: 1 | D2445: Contradict others | E2445: Disparagement
A2446: IPIP-IPC | C2446: 1 | D2446: Cut others to pieces. | E2446: Disparagement
A2447: IPIP-IPC | C2447: 1 | D2447: Demand attention | E2447: Dominance
A2448: IPIP-IPC | C2448: 1 | D2448: Demand to be the center of interest. | E2448: Dominance
A2449: IPIP-IPC | C2449: 1 | D2449: Dislike being the center of attention | E2449: Submissiveness
A2450: IPIP-IPC | C2450: 1 | D2450: Do most of the talking. | E2450: Dominance
A2451: IPIP-IPC | C2451: 1 | D2451: Don't fall for sob stories. | E2451: Callousness
... A2471: IPIP-IPC | C2471: 1 | D2471: Tolerate a lot from others. | E2471: Tolerance
A2472: JPI | B2472: 0.81 | C2472: 1 | D2472: Accomplish a lot of work. | E2472: Activity-Level
A2473: JPI | B2473: 0.78 | C2473: -1 | D2473: Am a very private person. | E2473: Sociability
A2474: JPI | B2474: 0.81 | C2474: 1 | D2474: Am always busy. | E2474: Activity-Level
A2475: JPI | B2475: 0.81 | C2475: 1 | D2475: Am always on the go. | E2475: Activity-Level
A2476: JPI | B2476: 0.8 | C2476: 1 | D2476: Am deeply moved by others' misfortunes. | E2476: Empathy
A2477: JPI | B2477: 0.87 | C2477: 1 | D2477: Am devoted to religion. | E2477: Traditionalism
A2478: JPI | B2478: 0.81 | C2478: -1 | D2478: Am easily discouraged. | E2478: Activity-Level
A2479: JPI | B2479: 0.8 | C2479: 1 | D2479: Am easily moved to tears. | E2479: Empathy
A2480: JPI | B2480: 0.87 | C2480: 1 | D2480: Am good at making impromptu speeches. | E2480: Social-confidence
A2481: JPI | B2481: 0.79 | C2481: 1 | D2481: Am interested in many things. | E2481: Intellectual-Breadth
A2482: JPI | B2482: 0.78 | C2482: 1 | D2482: Am interested in people. | E2482: Sociability
A2483: JPI | B2483: 0.71 | C2483: -1 | D2483: Am not concerned with making a good impression. | E2483: Conformity/Dependence/Need for approval
... A3806: VIA | B3806: 0.7 | C3806: 1 | D3806: Would never be described as arrogant. | E3806: Modesty/Humility

Sheet IPIP_items-zh-tw
A1: instrument | B1: alpha | C1: key | D1: text | E1: label
A2: 16PF | B2: 0.78 | C2: 1 | D2: 行為狂野瘋狂。 | E2: 合群性
A3: 16PF | B3: 0.8 | C3: 1 | D3: 我擔心自己會做錯事。 | E3: 焦慮
A4: 16PF | B4: 0.76 | C4: 1 | D4: 我會因他人的錯誤而感到煩躁。 | E4: 情緒性
A5: 16PF | B5: 0.85 | C5: -1 | D5: 我容易感到沮喪。 | E5: 情緒穩定性
A6: 16PF | B6: 0.8 | C6: 1 | D6: 我容易受傷。 | E6: 焦慮
A7: 16PF | B7: 0.76 | C7: 1 | D7: 我容易生氣。 | E7: 情緒性
A8: 16PF | B8: 0.81 | C8: 1 | D8: 我對工作要求嚴格。 | E8: 條理性
A9: 16PF | B9: 0.86 | C9: 1 | D9: 我很難被了解。 | E9: 保守性
A10: 16PF | B10: 0.81 | C10: 1 | D10: 我不怕提出批評。 | E10: 支配性
A11: 16PF | B11: 0.81 | C11: 1 | D11: 我不怕提出批評。 | E11: 自信堅定
A12: 16PF | B12: 0.81 | C12: -1 | D12: 我不會被混亂所困擾。 | E12: 條理性
A13: 16PF | B13: 0.81 | C13: -1 | D13: 我不會被凌亂的人困擾。 | E13: 條理性
... A920: AB5C | B920: 0.71 | C920: 1 | D920: 我不會傷害一隻蒼蠅。 | E920: 培育
A921: Barchard2001 | C921: -1 | D921: 即使在緊張的情況下我也很冷靜。 | E921: 反應性苦惱
A922: Barchard2001 | C922: 1 | D922: 我關心他人。 | E922: 同理心
A923: Barchard2001 | C923: 1 | D923: 我深受他人的不幸所感動。 | E923: 反應性苦惱
A924: Barchard2001 | C924: 1 | D924: 我容易被感動而流淚。 | E924: 反應性苦惱
A925: Barchard2001 | C925: -1 | D925: 我不容易被事件所困擾。 | E925: 反應性苦惱
A926: Barchard2001 | C926: -1 | D926: 我與自己的感受脫節。 | E926: 情緒關注
A927: Barchard2001 | C927: 1 | D927: 我受到他人良好情緒的強烈影響。 | E927: 反應性喜悅
A928: Barchard2001 | C928: -1 | D928: 我不受他人幸福的影響。 | E928: 反應性喜悅
A929: Barchard2001 | C929: -1 | D929: 我不受他人痛苦的影響。 | E929: 反應性苦惱
A930: Barchard2001 | C930: 1 | D930: 我為陌生人的不幸感到難過。 | E930: 反應性苦惱
A931: Barchard2001 | C931: 1 | D931: 我通常意識到自己的感受。 | E931: 情緒關注
A932: Barchard2001 | C932: 1 | D932: 我的人生目標基於啟發而非邏輯。 | E932: 基於情緒的決策
... A988: Barchard2001 | C988: 1 | D988: 如果我看到受傷的動物，我會感到難過。 | E988: 反應性苦惱
A989: BFAS | B989: 0.81 | C989: 1 | D989: 我總是知道自己在做什麼。 | E989: 勤勉/堅持/毅力
A990: BFAS | B990: 0.89 | C990: 1 | D990: 我是個情緒起伏的人。 | E990: 神經質
A991: BFAS | B991: 0.89 | C991: 1 | D991: 我是個情緒起伏的人。 | E991: 憤怒
A992: BFAS | B992: 0.89 | C992: 1 | D992: 我害怕很多事情。 | E992: 神經質
A993: BFAS | B993: 0.84 | C993: 1 | D993: 我害怕很多事情。 | E993: 焦慮
A994: BFAS | B994: 0.89 | C994: 1 | D994: 我容易感到沮喪。 | E994: 神經質
A995: BFAS | B995: 0.84 | C995: 1 | D995: 我容易感到沮喪。 | E995: 焦慮
A996: BFAS | B996: 0.81 | C996: -1 | D996: 我容易分心。 | E996: 勤勉/堅持/毅力
A997: BFAS | B997: 0.89 | C997: 1 | D997: 我對事情充滿疑慮。 | E997: 神經質
A998: BFAS | B998: 0.84 | C998: 1 | D998: 我對事情充滿疑慮。 | E998: 焦慮
A999: BFAS | B999: 0.81 | C999: -1 | D999: 我很難被了解。 | E999: 活力/熱情/熱忱
A1000: BFAS | B1000: 0.84 | C1000: -1 | D1000: 我對他人的感受漠不關心。 | E1000: 同情心
... A1290: Cacioppo1982 | B1290: 0.93 | C1290: -1 | D1290: 我試圖避開複雜的人。 | E1290: 認知需求
A1291: CAT-PD | C1291: 1 | D1291: 我不做計劃就行動。 | E1291: 非計劃性
A1292: CAT-PD | C1292: 1 | D1292: 我是個冷酷無情的人。 | E1292: 冷漠
A1293: CAT-PD | C1293: -1 | D1293: 我堅信要深思熟慮。 | E1293: 非計劃性
A1294: CAT-PD | C1294: -1 | D1294: 我是個守法的公民。 | E1294: 違反規範
A1295: CAT-PD | C1295: 1 | D1295: 我是個奇怪的人。 | E1295: 怪異
A1296: CAT-PD | C1296: -1 | D1296: 我是個非常可靠的人。 | E1296: 不負責任
A1297: CAT-PD | C1297: 1 | D1297: 我是個工作狂，沒什麼時間享樂。 | E1297: 工作狂
A1298: CAT-PD | C1298: -1 | D1298: 我能輕易描述自己的感受。 | E1298: 情感疏離
A1299: CAT-PD | C1299: 1 | D1299: 我能讀懂他人的心思。 | E1299: 非理性信念
A1300: CAT-PD | C1300: 1 | D1300: 我擔心我的生命會被疾病縮短。 | E1300: 健康焦慮
A1301: CAT-PD | C1301: 1 | D1301: 我總是擔心伴侶會離開我。 | E1301: 關係不安全感
A1302: CAT-PD | C1302: -1 | D1302: 我是個精力充沛的人。 | E1302: 快感缺失
... A1500: CAT-PD | C1500: 1 | D1500: 我會做任何事來獲得腎上腺素激增。 | E1500: 冒險/尋求感覺/尋求刺激
A1501: Chapman1986 | B1501: 0.77 | C1501: 1 | D1501: 我是個情緒起伏的人。 | E1501: 躁狂情緒強度
A1502: Chapman1986 | B1502: 0.77 | C1502: 1 | D1502: 我被認為有點古怪。 | E1502: 躁狂情緒強度
A1503: Chapman1986 | B1503: 0.81 | C1503: 1 | D1503: 我經常如此自信或善於社交，以至於我自己都感到驚訝。 | E1503: 躁狂表現慾
A1504: Chapman1986 | B1504: 0.77 | C1504: 1 | D1504: 我經常如此躁動，以至於我不可能坐著不動。 | E1504: 躁狂情緒強度
A1505: Chapman1986 | B1505: 0.81 | C1505: 1 | D1505: 我如此擅長控制他人，有時會嚇到我自己。 | E1505: 躁狂表現慾
A1506: Chapman1986 | B1506: 0.77 | C1506: -1 | D1506: 我通常處於一般的心情，不太高也不太低。 | E1506: 躁狂情緒強度
A1507: Chapman1986 | B1507: 0.81 | C1507: 1 | D1507: 我能令人信服地扮演許多角色。 | E1507: 躁狂表現慾
A1508: Chapman1986 | B1508: 0.77 | C1508: -1 | D1508: 我想慢下來時可以慢下來。 | E1508: 躁狂情緒強度
A1509: Chapman1986 | B1509: 0.81 | C1509: 1 | D1509: 我能在許多領域取得成功。 | E1509: 躁狂表現慾
A1510: Chapman1986 | B1510: 0.77 | C1510: 1 | D1510: 我以極度的強度感受情緒。 | E1510: 躁狂情緒強度
A1511: Chapman1986 | B1511: 0.77 | C1511: 1 | D1511: 我發現我的想法在奔馳。 | E1511: 躁狂情緒強度
A1512: Chapman1986 | B1512: 0.77 | C1512: 1 | D1512: 我陷入感到非常加速和煩躁的心情。 | E1512: 躁狂情緒強度
... A2439: HPI-HIC | B2439: 0.81 | C2439: -1 | D2439: 我會對人大吼。 | E2439: 冷靜頭腦
A2440: IPIP-IPC | C2440: 1 | D2440: 我是個非常隱私的人。 | E2440: 內向性
A2441: IPIP-IPC | C2441: 1 | D2441: 我對人感興趣。 | E2441: 熱情
A2442: IPIP-IPC | C2442: 1 | D2442: 我對他人的問題不感興趣。 | E2442: 冷漠
A2443: IPIP-IPC | C2443: 1 | D2443: 我在陌生人面前很安靜。 | E2443: 內向性
A2444: IPIP-IPC | C2444: 1 | D2444: 我相信人們應該自食其力。 | E2444: 冷漠
A2445: IPIP-IPC | C2445: 1 | D2445: 我反駁他人。 | E2445: 貶低
A2446: IPIP-IPC | C2446: 1 | D2446: 我會將他人批評得體無完膚。 | E2446: 貶低
A2447: IPIP-IPC | C2447: 1 | D2447: 我要求注意力。 | E2447: 支配性
A2448: IPIP-IPC | C2448: 1 | D2448: 我要求成為關注的焦點。 | E2448: 支配性
A2449: IPIP-IPC | C2449: 1 | D2449: 我不喜歡成為注意力的焦點。 | E2449: 順從性
A2450: IPIP-IPC | C2450: 1 | D2450: 我主導大部分談話。 | E2450: 支配性
A2451: IPIP-IPC | C2451: 1 | D2451: 我不會被悲傷的故事所動。 | E2451: 冷漠
... A2471: IPIP-IPC | C2471: 1 | D2471: 我容忍他人很多事。 | E2471: 容忍
A2472: JPI | B2472: 0.81 | C2472: 1 | D2472: 我完成很多工作。 | E2472: 活動水平
A2473: JPI | B2473: 0.78 | C2473: -1 | D2473: 我是個非常隱私的人。 | E2473: 社交性
A2474: JPI | B2474: 0.81 | C2474: 1 | D2474: 我總是很忙碌。 | E2474: 活動水平
A2475: JPI | B2475: 0.81 | C2475: 1 | D2475: 我總是在行動中。 | E2475: 活動水平
A2476: JPI | B2476: 0.8 | C2476: 1 | D2476: 我深受他人的不幸所感動。 | E2476: 同理心
A2477: JPI | B2477: 0.87 | C2477: 1 | D2477: 我虔誠信仰宗教。 | E2477: 傳統主義
A2478: JPI | B2478: 0.81 | C2478: -1 | D2478: 我容易感到沮喪。 | E2478: 活動水平
A2479: JPI | B2479: 0.8 | C2479: 1 | D2479: 我容易被感動而流淚。 | E2479: 同理心
A2480: JPI | B2480: 0.87 | C2480: 1 | D2480: 我擅長即興演講。 | E2480: 社交自信
A2481: JPI | B2481: 0.79 | C2481: 1 | D2481: 我對許多事物感興趣。 | E2481: 智識廣度
A2482: JPI | B2482: 0.78 | C2482: 1 | D2482: 我對人感興趣。 | E2482: 社交性
A2483: JPI | B2483: 0.71 | C2483: -1 | D2483: 我不在意給人留下好印象。 | E2483: 順從/依賴/需要認可
... A3806: VIA | B3806: 0.7 | C3806: 1 | D3806: 我永遠不會被形容為傲慢。 | E3806: 謙虛/謙遜

Sheet IPIP3320
A1: Survey | B1: ItemNumber
A2: Abuse people's confidences. | B2: H1131
A3: Accept apologies easily. | B3: H133
A4: Accept challenging tasks. | B4: H515
A5: Accept little from others. | B5: H615
A6: Accept others' weaknesses. | B6: H139
A7: Accept people as they are. | B7: H106
A8: Accept the consequences of my actions. | B8: H266
A9: Accept the first thing that comes along. | B9: H1384
A10: Accept what others say. | B10: H962
A11: Accomplish a lot of work. | B11: H554
A12: Accomplish my work on time. | B12: H230
... A3321: Yell at people. | B3321: H809

Sheet IPIP_merging
A1: instrument | B1: alpha | C1: alpha2 | D1: key | E1: text_en | F1: text_zh | G1: label | H1: label_zh | I1: IPIP_item_number
A2: 16PF | B2: 0.78 | D2: 1 | E2: Act wild and crazy. | F2: 行為狂野瘋狂。 | G2: Gregariousness | H2: 合群性 | I2: =_xlfn.XLOOKUP(E2,IPIP3320!A:A,IPIP3320!B:B,"") -> H871
A3: 16PF | B3: 0.8 | D3: 1 | E3: Am afraid that I will do the wrong thing. | F3: 我擔心自己會做錯事。 | G3: Anxiety | H3: 焦慮 | I3: =_xlfn.XLOOKUP(E3,IPIP3320!A:A,IPIP3320!B:B,"") -> H905
A4: 16PF | B4: 0.76 | D4: 1 | E4: Am annoyed by others' mistakes. | F4: 我會因他人的錯誤而感到煩躁。 | G4: Emotionality | H4: 情緒性 | I4: =_xlfn.XLOOKUP(E4,IPIP3320!A:A,IPIP3320!B:B,"") -> E82
A5: 16PF | B5: 0.85 | D5: -1 | E5: Am easily discouraged. | F5: 我容易感到沮喪。 | G5: Emotional Stability | H5: 情緒穩定性 | I5: =_xlfn.XLOOKUP(E5,IPIP3320!A:A,IPIP3320!B:B,"") -> H647
A6: 16PF | B6: 0.8 | D6: 1 | E6: Am easily hurt. | F6: 我容易受傷。 | G6: Anxiety | H6: 焦慮 | I6: =_xlfn.XLOOKUP(E6,IPIP3320!A:A,IPIP3320!B:B,"") -> H987
A7: 16PF | B7: 0.76 | D7: 1 | E7: Am easily put out. | F7: 我容易生氣。 | G7: Emotionality | H7: 情緒性 | I7: =_xlfn.XLOOKUP(E7,IPIP3320!A:A,IPIP3320!B:B,"") -> H641
A8: 16PF | B8: 0.81 | D8: 1 | E8: Am exacting in my work. | F8: 我對工作要求嚴格。 | G8: Orderliness | H8: 條理性 | I8: =_xlfn.XLOOKUP(E8,IPIP3320!A:A,IPIP3320!B:B,"") -> X163
A9: 16PF | B9: 0.86 | D9: 1 | E9: Am hard to get to know. | F9: 我很難被了解。 | G9: Reserve | H9: 保守性 | I9: =_xlfn.XLOOKUP(E9,IPIP3320!A:A,IPIP3320!B:B,"") -> H596, X9
A10: 16PF | B10: 0.81 | D10: 1 | E10: Am not afraid of providing criticism. | F10: 我不怕提出批評。 | G10: Dominance | H10: 支配性 | I10: =_xlfn.XLOOKUP(E10,IPIP3320!A:A,IPIP3320!B:B,"") -> H459
A11: 16PF | B11: 0.81 | D11: 1 | E11: Am not afraid of providing criticism. | F11: 我不怕提出批評。 | G11: Assertiveness | H11: 自信堅定 | I11: =_xlfn.XLOOKUP(E11,IPIP3320!A:A,IPIP3320!B:B,"") -> H459
A12: 16PF | B12: 0.81 | D12: -1 | E12: Am not bothered by disorder. | F12: 我不會被混亂所困擾。 | G12: Orderliness | H12: 條理性 | I12: =_xlfn.XLOOKUP(E12,IPIP3320!A:A,IPIP3320!B:B,"") -> E7
A13: 16PF | B13: 0.81 | D13: -1 | E13: Am not bothered by messy people. | F13: 我不會被凌亂的人困擾。 | G13: Orderliness | H13: 條理性 | I13: =_xlfn.XLOOKUP(E13,IPIP3320!A:A,IPIP3320!B:B,"") -> E100
... A920: AB5C | B920: 0.71 | D920: 1 | E920: Wouldn't harm a fly. | F920: 我不會傷害一隻蒼蠅。 | G920: Nurturance | H920: 培育 | I920: =_xlfn.XLOOKUP(E920,IPIP3320!A:A,IPIP3320!B:B,"") -> H142
A921: Barchard2001 | B921: 0.59 | C921: 0.63 | D921: -1 | E921: Am calm even in tense situations. | F921: 即使在緊張的情況下我也很冷靜。 | G921: Responsive Distress | H921: 反應性苦惱 | I921: =_xlfn.XLOOKUP(E921,IPIP3320!A:A,IPIP3320!B:B,"") -> E64
A922: Barchard2001 | B922: 0.64 | C922: 0.8 | D922: 1 | E922: Am concerned about others. | F922: 我關心他人。 | G922: Empathy | H922: 同理心 | I922: =_xlfn.XLOOKUP(E922,IPIP3320!A:A,IPIP3320!B:B,"") -> H1100, X31
A923: Barchard2001 | B923: 0.59 | C923: 0.63 | D923: 1 | E923: Am deeply moved by others' misfortunes. | F923: 我深受他人的不幸所感動。 | G923: Responsive Distress | H923: 反應性苦惱 | I923: =_xlfn.XLOOKUP(E923,IPIP3320!A:A,IPIP3320!B:B,"") -> X253
A924: Barchard2001 | B924: 0.59 | C924: 0.63 | D924: 1 | E924: Am easily moved to tears. | F924: 我容易被感動而流淚。 | G924: Responsive Distress | H924: 反應性苦惱 | I924: =_xlfn.XLOOKUP(E924,IPIP3320!A:A,IPIP3320!B:B,"") -> H992
A925: Barchard2001 | B925: 0.59 | C925: 0.63 | D925: -1 | E925: Am not easily disturbed by events. | F925: 我不容易被事件所困擾。 | G925: Responsive Distress | H925: 反應性苦惱 | I925: =_xlfn.XLOOKUP(E925,IPIP3320!A:A,IPIP3320!B:B,"") -> H1046, X11
A926: Barchard2001 | B926: 0.81 | C926: 0.83 | D926: -1 | E926: Am not in touch with my feelings. | F926: 我與自己的感受脫節。 | G926: Attention to Emotions | H926: 情緒關注 | I926: =_xlfn.XLOOKUP(E926,IPIP3320!A:A,IPIP3320!B:B,"") -> E9
A927: Barchard2001 | B927: 0.73 | C927: 0.7 | D927: 1 | E927: Am strongly influenced by the good moods of others. | F927: 我受到他人良好情緒的強烈影響。 | G927: Responsive Joy | H927: 反應性喜悅 | I927: =_xlfn.XLOOKUP(E927,IPIP3320!A:A,IPIP3320!B:B,"") -> A72
A928: Barchard2001 | B928: 0.73 | C928: 0.7 | D928: -1 | E928: Am unaffected by other people's happiness. | F928: 我不受他人幸福的影響。 | G928: Responsive Joy | H928: 反應性喜悅 | I928: =_xlfn.XLOOKUP(E928,IPIP3320!A:A,IPIP3320!B:B,"") -> A11
A929: Barchard2001 | B929: 0.59 | C929: 0.63 | D929: -1 | E929: Am unaffected by the suffering of others. | F929: 我不受他人痛苦的影響。 | G929: Responsive Distress | H929: 反應性苦惱 | I929: =_xlfn.XLOOKUP(E929,IPIP3320!A:A,IPIP3320!B:B,"") -> A67
A930: Barchard2001 | B930: 0.59 | C930: 0.63 | D930: 1 | E930: Am upset by the misfortunes of strangers. | F930: 我為陌生人的不幸感到難過。 | G930: Responsive Distress | H930: 反應性苦惱 | I930: =_xlfn.XLOOKUP(E930,IPIP3320!A:A,IPIP3320!B:B,"") -> A135
A931: Barchard2001 | B931: 0.81 | C931: 0.83 | D931: 1 | E931: Am usually aware of the way that I'm feeling. | F931: 我通常意識到自己的感受。 | G931: Attention to Emotions | H931: 情緒關注 | I931: =_xlfn.XLOOKUP(E931,IPIP3320!A:A,IPIP3320!B:B,"") -> A122
A932: Barchard2001 | B932: 0.73 | C932: 0.67 | D932: 1 | E932: Base my goals in life on inspiration, rather than logic. | F932: 我的人生目標基於啟發而非邏輯。 | G932: Emotion-based Decision-making | H932: 基於情緒的決策 | I932: =_xlfn.XLOOKUP(E932,IPIP3320!A:A,IPIP3320!B:B,"") -> A26
... A988: Barchard2001 | B988: 0.59 | C988: 0.63 | D988: 1 | E988: Would be upset if I saw an injured animal. | F988: 如果我看到受傷的動物，我會感到難過。 | G988: Responsive Distress | H988: 反應性苦惱 | I988: =_xlfn.XLOOKUP(E988,IPIP3320!A:A,IPIP3320!B:B,"") -> A46
A989: BFAS | B989: 0.81 | D989: 1 | E989: Always know what I am doing. | F989: 我總是知道自己在做什麼。 | G989: Industriousness/Perseverance/Persistence | H989: 勤勉/堅持/毅力 | I989: =_xlfn.XLOOKUP(E989,IPIP3320!A:A,IPIP3320!B:B,"") -> P427
A990: BFAS | B990: 0.89 | D990: 1 | E990: Am a person whose moods go up and down easily. | F990: 我是個情緒起伏的人。 | G990: Neuroticism | H990: 神經質 | I990: =_xlfn.XLOOKUP(E990,IPIP3320!A:A,IPIP3320!B:B,"")
A991: BFAS | B991: 0.89 | D991: 1 | E991: Am a person whose moods go up and down easily. | F991: 我是個情緒起伏的人。 | G991: Anger | H991: 憤怒 | I991: =_xlfn.XLOOKUP(E991,IPIP3320!A:A,IPIP3320!B:B,"")
A992: BFAS | B992: 0.89 | D992: 1 | E992: Am afraid of many things. | F992: 我害怕很多事情。 | G992: Neuroticism | H992: 神經質 | I992: =_xlfn.XLOOKUP(E992,IPIP3320!A:A,IPIP3320!B:B,"") -> H968
A993: BFAS | B993: 0.84 | D993: 1 | E993: Am afraid of many things. | F993: 我害怕很多事情。 | G993: Anxiety | H993: 焦慮 | I993: =_xlfn.XLOOKUP(E993,IPIP3320!A:A,IPIP3320!B:B,"") -> H968
A994: BFAS | B994: 0.89 | D994: 1 | E994: Am easily discouraged. | F994: 我容易感到沮喪。 | G994: Neuroticism | H994: 神經質 | I994: =_xlfn.XLOOKUP(E994,IPIP3320!A:A,IPIP3320!B:B,"") -> H647
A995: BFAS | B995: 0.84 | D995: 1 | E995: Am easily discouraged. | F995: 我容易感到沮喪。 | G995: Anxiety | H995: 焦慮 | I995: =_xlfn.XLOOKUP(E995,IPIP3320!A:A,IPIP3320!B:B,"") -> H647
A996: BFAS | B996: 0.81 | D996: -1 | E996: Am easily distracted. | F996: 我容易分心。 | G996: Industriousness/Perseverance/Persistence | H996: 勤勉/堅持/毅力 | I996: =_xlfn.XLOOKUP(E996,IPIP3320!A:A,IPIP3320!B:B,"") -> H843, F44, T192
A997: BFAS | B997: 0.89 | D997: 1 | E997: Am filled with doubts about things. | F997: 我對事情充滿疑慮。 | G997: Neuroticism | H997: 神經質 | I997: =_xlfn.XLOOKUP(E997,IPIP3320!A:A,IPIP3320!B:B,"") -> H683
A998: BFAS | B998: 0.84 | D998: 1 | E998: Am filled with doubts about things. | F998: 我對事情充滿疑慮。 | G998: Anxiety | H998: 焦慮 | I998: =_xlfn.XLOOKUP(E998,IPIP3320!A:A,IPIP3320!B:B,"") -> H683
A999: BFAS | B999: 0.81 | D999: -1 | E999: Am hard to get to know. | F999: 我很難被了解。 | G999: Vitality/Enthusiasm/Zest | H999: 活力/熱情/熱忱 | I999: =_xlfn.XLOOKUP(E999,IPIP3320!A:A,IPIP3320!B:B,"") -> H596, X9
A1000: BFAS | B1000: 0.84 | D1000: -1 | E1000: Am indifferent to the feelings of others. | F1000: 我對他人的感受漠不關心。 | G1000: Compassion | H1000: 同情心 | I1000: =_xlfn.XLOOKUP(E1000,IPIP3320!A:A,IPIP3320!B:B,"") -> X203
... A1217: BIDR | B1217: 0.87 | D1217: 1 | E1217: Would never take things that aren't mine. | F1217: 我永遠不會拿不屬於我的東西。 | G1217: Impression-Management | H1217: 印象管理 | I1217: =_xlfn.XLOOKUP(E1217,IPIP3320!A:A,IPIP3320!B:B,"") -> P367
A1218: BIS_BAS | D1218: 1 | E1218: Am afraid that I will do the wrong thing. | F1218: 我擔心自己會做錯事。 | G1218: Behavioral Inhibition/Activation System | H1218: 行為抑制/激活系統 | I1218: =_xlfn.XLOOKUP(E1218,IPIP3320!A:A,IPIP3320!B:B,"") -> H905
A1219: BIS_BAS | D1219: 1 | E1219: Am always worried about something. | F1219: 我總是擔心某事。 | G1219: Behavioral Inhibition/Activation System | H1219: 行為抑制/激活系統 | I1219: =_xlfn.XLOOKUP(E1219,IPIP3320!A:A,IPIP3320!B:B,"") -> D96
A1220: BIS_BAS | D1220: 1 | E1220: Am always worried about something. | F1220: 我總是擔心某事。 | G1220: Anxiety | H1220: 焦慮 | I1220: =_xlfn.XLOOKUP(E1220,IPIP3320!A:A,IPIP3320!B:B,"") -> D96
A1221: BIS_BAS | B1221: 0.68 | D1221: 1 | E1221: Am eager to soothe hurt feelings. | F1221: 我渴望撫慰受傷的感受。 | G1221: Excitement-seeking | H1221: 尋求刺激 | I1221: =_xlfn.XLOOKUP(E1221,IPIP3320!A:A,IPIP3320!B:B,"") -> Q117
A1222: BIS_BAS | D1222: 1 | E1222: Am easily hurt. | F1222: 我容易受傷。 | G1222: Behavioral Inhibition/Activation System | H1222: 行為抑制/激活系統 | I1222: =_xlfn.XLOOKUP(E1222,IPIP3320!A:A,IPIP3320!B:B,"") -> H987
A1223: BIS_BAS | B1223: 0.77 | D1223: -1 | E1223: Am not an extraordinary person. | F1223: 我不是個非凡的人。 | G1223: Ambition/Drive | H1223: 野心/動力 | I1223: =_xlfn.XLOOKUP(E1223,IPIP3320!A:A,IPIP3320!B:B,"") -> P462
A1224: BIS_BAS | D1224: -1 | E1224: Am not embarrassed easily. | F1224: 我不容易感到尷尬。 | G1224: Behavioral Inhibition/Activation System | H1224: 行為抑制/激活系統 | I1224: =_xlfn.XLOOKUP(E1224,IPIP3320!A:A,IPIP3320!B:B,"") -> X242
A1225: BIS_BAS | B1225: 0.77 | D1225: -1 | E1225: Am not highly motivated to succeed. | F1225: 我沒有強烈的成功動機。 | G1225: Ambition/Drive | H1225: 野心/動力 | I1225: =_xlfn.XLOOKUP(E1225,IPIP3320!A:A,IPIP3320!B:B,"") -> X110
A1226: BIS_BAS | B1226: 0.79 | D1226: 1 | E1226: Am willing to try anything once. | F1226: 我願意嘗試任何事。 | G1226: Risk-taking/Sensation-Seeking/Thrill-Seeking | H1226: 冒險/尋求感覺/尋求刺激 | I1226: =_xlfn.XLOOKUP(E1226,IPIP3320!A:A,IPIP3320!B:B,"") -> X3
A1227: BIS_BAS | B1227: 0.79 | D1227: -1 | E1227: Avoid dangerous situations. | F1227: 我避免危險情況。 | G1227: Risk-taking/Sensation-Seeking/Thrill-Seeking | H1227: 冒險/尋求感覺/尋求刺激 | I1227: =_xlfn.XLOOKUP(E1227,IPIP3320!A:A,IPIP3320!B:B,"") -> H317
A1228: BIS_BAS | D1228: 1 | E1228: Become overwhelmed by events. | F1228: 我被事件壓倒。 | G1228: Behavioral Inhibition/Activation System | H1228: 行為抑制/激活系統 | I1228: =_xlfn.XLOOKUP(E1228,IPIP3320!A:A,IPIP3320!B:B,"") -> H959
A1229: BIS_BAS | D1229: 1 | E1229: Begin to panic when there is danger. | F1229: 當有危險時我開始驚慌。 | G1229: Behavioral Inhibition/Activation System | H1229: 行為抑制/激活系統 | I1229: =_xlfn.XLOOKUP(E1229,IPIP3320!A:A,IPIP3320!B:B,"") -> Q50
A1230: BIS_BAS | D1230: 1 | E1230: Begin to panic when there is danger. | F1230: 當有危險時我開始驚慌。 | G1230: Anxiety | H1230: 焦慮 | I1230: =_xlfn.XLOOKUP(E1230,IPIP3320!A:A,IPIP3320!B:B,"") -> Q50
A1231: BIS_BAS | B1231: 0.79 | D1231: 1 | E1231: Do crazy things. | F1231: 我做瘋狂的事情。 | G1231: Risk-taking/Sensation-Seeking/Thrill-Seeking | H1231: 冒險/尋求感覺/尋求刺激 | I1231: =_xlfn.XLOOKUP(E1231,IPIP3320!A:A,IPIP3320!B:B,"") -> H870
A1232: BIS_BAS | B1232: 0.68 | D1232: -1 | E1232: Don't get excited about things. | F1232: 我對事物不感到興奮。 | G1232: Excitement-seeking | H1232: 尋求刺激 | I1232: =_xlfn.XLOOKUP(E1232,IPIP3320!A:A,IPIP3320!B:B,"") -> H572
A1233: BIS_BAS | B1233: 0.79 | D1233: 1 | E1233: Enjoy being reckless. | F1233: 我喜歡冒險行事。 | G1233: Risk-taking/Sensation-Seeking/Thrill-Seeking | H1233: 冒險/尋求感覺/尋求刺激 | I1233: =_xlfn.XLOOKUP(E1233,IPIP3320!A:A,IPIP3320!B:B,"") -> E35
A1234: BIS_BAS | B1234: 0.68 | D1234: 1 | E1234: Feel excited or happy for no apparent reason. | F1234: 我無緣無故感到興奮或快樂。 | G1234: Excitement-seeking | H1234: 尋求刺激 | I1234: =_xlfn.XLOOKUP(E1234,IPIP3320!A:A,IPIP3320!B:B,"") -> R33
A1235: BIS_BAS | B1235: 0.68 | D1235: 1 | E1235: Get caught up in the excitement when others are celebrating. | F1235: 當他人慶祝時，我會被興奮感染。 | G1235: Excitement-seeking | H1235: 尋求刺激 | I1235: =_xlfn.XLOOKUP(E1235,IPIP3320!A:A,IPIP3320!B:B,"") -> A71
A1236: BIS_BAS | B1236: 0.68 | D1236: 1 | E1236: Get so happy or energetic that I am almost giddy. | F1236: 我變得如此快樂或精力充沛，幾乎有點頭暈。 | G1236: Excitement-seeking | H1236: 尋求刺激 | I1236: =_xlfn.XLOOKUP(E1236,IPIP3320!A:A,IPIP3320!B:B,"") -> R43
A1237: BIS_BAS | D1237: 1 | E1237: Get stressed out easily. | F1237: 我容易感到壓力。 | G1237: Behavioral Inhibition/Activation System | H1237: 行為抑制/激活系統 | I1237: =_xlfn.XLOOKUP(E1237,IPIP3320!A:A,IPIP3320!B:B,"") -> X107
A1238: BIS_BAS | D1238: 1 | E1238: Get stressed out easily. | F1238: 我容易感到壓力。 | G1238: Anxiety | H1238: 焦慮 | I1238: =_xlfn.XLOOKUP(E1238,IPIP3320!A:A,IPIP3320!B:B,"") -> X107
A1239: BIS_BAS | B1239: 0.77 | D1239: -1 | E1239: Hate being the center of attention. | F1239: 我討厭成為注意力的焦點。 | G1239: Ambition/Drive | H1239: 野心/動力 | I1239: =_xlfn.XLOOKUP(E1239,IPIP3320!A:A,IPIP3320!B:B,"") -> P434
A1240: BIS_BAS | B1240: 0.77 | D1240: 1 | E1240: Have a strong need for power. | F1240: 我有強烈的權力需求。 | G1240: Ambition/Drive | H1240: 野心/動力 | I1240: =_xlfn.XLOOKUP(E1240,IPIP3320!A:A,IPIP3320!B:B,"") -> P445
A1241: BIS_BAS | B1241: 0.79 | D1241: 1 | E1241: Have persuaded others to do something really adventurous or crazy. | F1241: 我說服他人做真正冒險或瘋狂的事。 | G1241: Risk-taking/Sensation-Seeking/Thrill-Seeking | H1241: 冒險/尋求感覺/尋求刺激 | I1241: =_xlfn.XLOOKUP(E1241,IPIP3320!A:A,IPIP3320!B:B,"") -> R58
A1242: BIS_BAS | B1242: 0.77 | D1242: 1 | E1242: Know how to get around the rules. | F1242: 我知道如何規避規則。 | G1242: Ambition/Drive | H1242: 野心/動力 | I1242: =_xlfn.XLOOKUP(E1242,IPIP3320!A:A,IPIP3320!B:B,"") -> H1327
A1243: BIS_BAS | B1243: 0.79 | D1243: 1 | E1243: Like to act on a whim. | F1243: 我喜歡憑一時衝動行事。 | G1243: Risk-taking/Sensation-Seeking/Thrill-Seeking | H1243: 冒險/尋求感覺/尋求刺激 | I1243: =_xlfn.XLOOKUP(E1243,IPIP3320!A:A,IPIP3320!B:B,"") -> E122
A1244: BIS_BAS | B1244: 0.79 | D1244: 1 | E1244: Like to behave spontaneously. | F1244: 我喜歡自發地行為。 | G1244: Risk-taking/Sensation-Seeking/Thrill-Seeking | H1244: 冒險/尋求感覺/尋求刺激 | I1244: =_xlfn.XLOOKUP(E1244,IPIP3320!A:A,IPIP3320!B:B,"") -> D58
A1245: BIS_BAS | B1245: 0.77 | D1245: 1 | E1245: Like to show off my body. | F1245: 我喜歡炫耀我的身體。 | G1245: Ambition/Drive | H1245: 野心/動力 | I1245: =_xlfn.XLOOKUP(E1245,IPIP3320!A:A,IPIP3320!B:B,"") -> P474
A1246: BIS_BAS | D1246: 1 | E1246: Often worry about things that turn out to be unimportant. | F1246: 我經常擔心事後證明不重要的事情。 | G1246: Behavioral Inhibition/Activation System | H1246: 行為抑制/激活系統 | I1246: =_xlfn.XLOOKUP(E1246,IPIP3320!A:A,IPIP3320!B:B,"") -> D71
A1247: BIS_BAS | D1247: 1 | E1247: Often worry about things that turn out to be unimportant. | F1247: 我經常擔心事後證明不重要的事情。 | G1247: Anxiety | H1247: 焦慮 | I1247: =_xlfn.XLOOKUP(E1247,IPIP3320!A:A,IPIP3320!B:B,"") -> D71
A1248: BIS_BAS | B1248: 0.79 | D1248: 1 | E1248: Prefer friends who are excitingly unpredictable. | F1248: 我喜歡令人興奮且不可預測的朋友。 | G1248: Risk-taking/Sensation-Seeking/Thrill-Seeking | H1248: 冒險/尋求感覺/尋求刺激 | I1248: =_xlfn.XLOOKUP(E1248,IPIP3320!A:A,IPIP3320!B:B,"") -> R5
A1249: BIS_BAS | B1249: 0.77 | D1249: 1 | E1249: Push myself very hard to succeed. | F1249: 我非常努力地推動自己成功。 | G1249: Ambition/Drive | H1249: 野心/動力 | I1249: =_xlfn.XLOOKUP(E1249,IPIP3320!A:A,IPIP3320!B:B,"") -> Q204
A1250: BIS_BAS | B1250: 0.79 | D1250: -1 | E1250: Rarely enjoy behaving in a silly manner. | F1250: 我很少享受以愚蠢的方式行為。 | G1250: Risk-taking/Sensation-Seeking/Thrill-Seeking | H1250: 冒險/尋求感覺/尋求刺激 | I1250: =_xlfn.XLOOKUP(E1250,IPIP3320!A:A,IPIP3320!B:B,"") -> D75
A1251: BIS_BAS | B1251: 0.68 | D1251: -1 | E1251: Rarely get caught up in the excitement. | F1251: 我很少被興奮感染。 | G1251: Excitement-seeking | H1251: 尋求刺激 | I1251: =_xlfn.XLOOKUP(E1251,IPIP3320!A:A,IPIP3320!B:B,"") -> A13
A1252: BIS_BAS | D1252: -1 | E1252: Rarely worry. | F1252: 我很少擔心。 | G1252: Behavioral Inhibition/Activation System | H1252: 行為抑制/激活系統 | I1252: =_xlfn.XLOOKUP(E1252,IPIP3320!A:A,IPIP3320!B:B,"") -> D79
A1253: BIS_BAS | D1253: -1 | E1253: Rarely worry. | F1253: 我很少擔心。 | G1253: Anxiety | H1253: 焦慮 | I1253: =_xlfn.XLOOKUP(E1253,IPIP3320!A:A,IPIP3320!B:B,"") -> D79
A1254: BIS_BAS | B1254: 0.77 | D1254: 1 | E1254: Take charge. | F1254: 我會掌控。 | G1254: Ambition/Drive | H1254: 野心/動力 | I1254: =_xlfn.XLOOKUP(E1254,IPIP3320!A:A,IPIP3320!B:B,"") -> H334, X27
A1255: BIS_BAS | B1255: 0.77 | D1255: 1 | E1255: Try to surpass others' accomplishments. | F1255: 我試圖超越他人的成就。 | G1255: Ambition/Drive | H1255: 野心/動力 | I1255: =_xlfn.XLOOKUP(E1255,IPIP3320!A:A,IPIP3320!B:B,"") -> H1193
A1256: BIS_BAS | B1256: 0.77 | D1256: 1 | E1256: Want to be in charge. | F1256: 我想要掌控。 | G1256: Ambition/Drive | H1256: 野心/動力 | I1256: =_xlfn.XLOOKUP(E1256,IPIP3320!A:A,IPIP3320!B:B,"") -> H793
A1257: BIS_BAS | D1257: 1 | E1257: Worry about what people think of me. | F1257: 我擔心人們對我的看法。 | G1257: Behavioral Inhibition/Activation System | H1257: 行為抑制/激活系統 | I1257: =_xlfn.XLOOKUP(E1257,IPIP3320!A:A,IPIP3320!B:B,"") -> P420
A1258: BIS_BAS | D1258: 1 | E1258: Worry about what people think of me. | F1258: 我擔心人們對我的看法。 | G1258: Anxiety | H1258: 焦慮 | I1258: =_xlfn.XLOOKUP(E1258,IPIP3320!A:A,IPIP3320!B:B,"") -> P420
A1259: BIS_BAS | B1259: 0.79 | D1259: -1 | E1259: Would never go hang gliding or bungee jumping. | F1259: 我永遠不會去滑翔傘或高空彈跳。 | G1259: Risk-taking/Sensation-Seeking/Thrill-Seeking | H1259: 冒險/尋求感覺/尋求刺激 | I1259: =_xlfn.XLOOKUP(E1259,IPIP3320!A:A,IPIP3320!B:B,"")
A1260: Buss1980 | B1260: 0.81 | D1260: 1 | E1260: Am constantly reflecting about myself. | F1260: 我不斷反思自己。 | G1260: Introspection/Private Self-Consciousness | H1260: 內省/私人自我意識 | I1260: =_xlfn.XLOOKUP(E1260,IPIP3320!A:A,IPIP3320!B:B,"") -> P395
A1261: Buss1980 | B1261: 0.77 | D1261: 1 | E1261: Am easily intimidated. | F1261: 我容易被威脅。 | G1261: Public Self-consciousness | H1261: 公眾自我意識 | I1261: =_xlfn.XLOOKUP(E1261,IPIP3320!A:A,IPIP3320!B:B,"") -> H991, X41
A1262: Buss1980 | B1262: 0.77 | D1262: -1 | E1262: Am not concerned with making a good impression. | F1262: 我不在意給人留下好印象。 | G1262: Public Self-consciousness | H1262: 公眾自我意識 | I1262: =_xlfn.XLOOKUP(E1262,IPIP3320!A:A,IPIP3320!B:B,"") -> P397
A1263: Buss1980 | B1263: 0.77 | D1263: -1 | E1263: Am not easily bothered by things. | F1263: 我不容易被事情困擾。 | G1263: Public Self-consciousness | H1263: 公眾自我意識 | I1263: =_xlfn.XLOOKUP(E1263,IPIP3320!A:A,IPIP3320!B:B,"") -> X138
A1264: Buss1980 | B1264: 0.77 | D1264: -1 | E1264: Am not embarrassed easily. | F1264: 我不容易感到尷尬。 | G1264: Public Self-consciousness | H1264: 公眾自我意識 | I1264: =_xlfn.XLOOKUP(E1264,IPIP3320!A:A,IPIP3320!B:B,"") -> X242
A1265: Buss1980 | B1265: 0.81 | D1265: -1 | E1265: Don't try to figure myself out. | F1265: 我不試圖弄清楚自己。 | G1265: Introspection/Private Self-Consciousness | H1265: 內省/私人自我意識 | I1265: =_xlfn.XLOOKUP(E1265,IPIP3320!A:A,IPIP3320!B:B,"") -> P363
A1266: Buss1980 | B1266: 0.77 | D1266: -1 | E1266: Don't worry about things that have already happened. | F1266: 我不擔心已經發生的事情。 | G1266: Public Self-consciousness | H1266: 公眾自我意識 | I1266: =_xlfn.XLOOKUP(E1266,IPIP3320!A:A,IPIP3320!B:B,"") -> E150
A1267: Buss1980 | B1267: 0.81 | D1267: 1 | E1267: Examine my motives constantly. | F1267: 我不斷審查自己的動機。 | G1267: Introspection/Private Self-Consciousness | H1267: 內省/私人自我意識 | I1267: =_xlfn.XLOOKUP(E1267,IPIP3320!A:A,IPIP3320!B:B,"") -> P377
A1268: Buss1980 | B1268: 0.77 | D1268: -1 | E1268: Feel comortable with myself. | F1268: 我對自己感到自在。 | G1268: Public Self-consciousness | H1268: 公眾自我意識 | I1268: =_xlfn.XLOOKUP(E1268,IPIP3320!A:A,IPIP3320!B:B,"")
A1269: Buss1980 | B1269: 0.77 | D1269: 1 | E1269: Feel threatened easily. | F1269: 我容易感到威脅。 | G1269: Public Self-consciousness | H1269: 公眾自我意識 | I1269: =_xlfn.XLOOKUP(E1269,IPIP3320!A:A,IPIP3320!B:B,"") -> H612
A1270: Buss1980 | B1270: 0.81 | D1270: 1 | E1270: Like to get lost in thought. | F1270: 我喜歡陷入沉思。 | G1270: Introspection/Private Self-Consciousness | H1270: 內省/私人自我意識 | I1270: =_xlfn.XLOOKUP(E1270,IPIP3320!A:A,IPIP3320!B:B,"") -> E163
... A1290: Cacioppo1982 | B1290: 0.93 | D1290: -1 | E1290: Try to avoid complex people. | F1290: 我試圖避開複雜的人。 | G1290: Need for Cognition | H1290: 認知需求 | I1290: =_xlfn.XLOOKUP(E1290,IPIP3320!A:A,IPIP3320!B:B,"") -> E171
A1291: CAT-PD | B1291: 0.82 | C1291: 0.84 | D1291: 1 | E1291: Act without planning. | F1291: 我不做計劃就行動。 | G1291: Non-Planfulness | H1291: 非計劃性 | I1291: =_xlfn.XLOOKUP(E1291,IPIP3320!A:A,IPIP3320!B:B,"") -> H848
A1292: CAT-PD | B1292: 0.85 | C1292: 0.83 | D1292: 1 | E1292: Am a cold-hearted person. | F1292: 我是個冷酷無情的人。 | G1292: Callousness | H1292: 冷漠 | I1292: =_xlfn.XLOOKUP(E1292,IPIP3320!A:A,IPIP3320!B:B,"") -> T63
A1293: CAT-PD | B1293: 0.82 | C1293: 0.84 | D1293: -1 | E1293: Am a firm believer in thinking things through. | F1293: 我堅信要深思熟慮。 | G1293: Non-Planfulness | H1293: 非計劃性 | I1293: =_xlfn.XLOOKUP(E1293,IPIP3320!A:A,IPIP3320!B:B,"")
A1294: CAT-PD | B1294: 0.83 | C1294: 0.84 | D1294: -1 | E1294: Am a law-abiding citizen. | F1294: 我是個守法的公民。 | G1294: Norm Violation | H1294: 違反規範 | I1294: =_xlfn.XLOOKUP(E1294,IPIP3320!A:A,IPIP3320!B:B,"") -> T81
A1295: CAT-PD | B1295: 0.86 | C1295: 0.82 | D1295: 1 | E1295: Am a strange person. | F1295: 我是個奇怪的人。 | G1295: Peculiarity | H1295: 怪異 | I1295: =_xlfn.XLOOKUP(E1295,IPIP3320!A:A,IPIP3320!B:B,"") -> T99
A1296: CAT-PD | B1296: 0.82 | C1296: 0.85 | D1296: -1 | E1296: Am a very reliable person. | F1296: 我是個非常可靠的人。 | G1296: Irresponsibility | H1296: 不負責任 | I1296: =_xlfn.XLOOKUP(E1296,IPIP3320!A:A,IPIP3320!B:B,"") -> T103
...

Sheet LABEL_grouping
A3: label | B3: label_zh
A4: Achievement-striving | B4: 成就追求 | E4: =G4=A4 -> TRUE | G4: Achievement-striving
A5: Activity-Level | B5: 活動水平 | E5: =G5=A5 -> TRUE | G5: Activity-Level
A6: Adaptability | B6: 適應性 | E6: =G6=A6 -> TRUE | G6: Adaptability
A7: ADHD | B7: ADHD | E7: =G7=A7 -> TRUE | G7: ADHD
A8: Adventurousness | B8: 冒險性 | E8: =G8=A8 -> TRUE | G8: Adventurousness
A9: Aesthetic Appreciation/Artistic Interests | B9: 美學欣賞/藝術興趣 | E9: =G9=A9 -> TRUE | G9: Aesthetic Appreciation/Artistic Interests
A10: Affective Lability | B10: 情感不穩定 | E10: =G10=A10 -> TRUE | G10: Affective Lability
A11: Agreeableness | B11: 親和性 | E11: =G11=A11 -> TRUE | G11: Agreeableness
A12: Altruism | B12: 利他主義 | E12: =G12=A12 -> TRUE | G12: Altruism
A13: Ambition/Drive | B13: 野心/動力 | E13: =G13=A13 -> TRUE | G13: Ambition/Drive
A14: Amiability | B14: 和藹 | E14: =G14=A14 -> TRUE | G14: Amiability
A15: Anger | B15: 憤怒 | E15: =G15=A15 -> TRUE | G15: Anger
... A249: Workaholism | B249: 工作狂 | E249: =G249=A249 -> TRUE | G249: Workaholism

Sheet instrument_grouping
A3: 列標籤 | B3: 計數 - instrument
A4: 16PF | B4: 172 | D4: 16PF | F4: =A4=D4 -> TRUE
A5: 6FPQ | B5: 229 | D5: 6FPQ | F5: =A5=D5 -> TRUE
A6: 7FACTOR | B6: 62 | D6: 7FACTOR | F6: =A6=D6 -> TRUE
A7: AB5C | B7: 456 | D7: AB5C | F7: =A7=D7 -> TRUE
A8: Barchard2001 | B8: 68 | D8: Barchard2001 | F8: =A8=D8 -> TRUE
A9: BFAS | B9: 125 | D9: BFAS | F9: =A9=D9 -> TRUE
A10: BFAS-20 | B10: 64 | D10: BFAS-20 | F10: =A10=D10 -> TRUE
A11: BIDR | B11: 40 | D11: BIDR | F11: =A11=D11 -> TRUE
A12: BIS_BAS | B12: 42 | D12: BIS_BAS | F12: =A12=D12 -> TRUE
A13: Buss1980 | B13: 21 | D13: Buss1980 | F13: =A13=D13 -> TRUE
A14: Cacioppo1982 | B14: 10 | D14: Cacioppo1982 | F14: =A14=D14 -> TRUE
A15: CAT-PD | B15: 210 | D15: CAT-PD | F15: =A15=D15 -> TRUE
... A39: VIA | B39: 252 | D39: VIA | F39: =A39=D39 -> TRUE
A40: 總計 | B40: 3805
