Workbook

Sheet 工作表5
A3: 計數 - text | B3: 欄標籤
A4: 列標籤 | B4: -1 | C4: 0 | D4: 1 | E4: 總計
A5: Achievement-striving | B5: 10 | D5: 22 | E5: 32
A6: Activity-Level | B6: 10 | D6: 6 | E6: 16
A7: Adaptability | B7: 5 | D7: 3 | E7: 8
A8: ADHD | D8: 12 | E8: 12
A9: Adventurousness | B9: 12 | D9: 23 | E9: 35
A10: Aesthetic Appreciation/Artistic Interests | B10: 9 | C10: 2 | D10: 17 | E10: 28
A11: Affective Lability | B11: 2 | D11: 4 | E11: 6
A12: Agreeableness | B12: 20 | D12: 26 | E12: 46
A13: Altruism | B13: 5 | D13: 18 | E13: 23
A14: Ambition/Drive | B14: 3 | D14: 7 | E14: 10
A15: Amiability | B15: 5 | D15: 5 | E15: 10
A16: Anger | B16: 8 | D16: 11 | E16: 19
A17: Anhedonia | B17: 2 | D17: 4 | E17: 6
A18: Anxiety | B18: 14 | D18: 28 | E18: 42
A19: Appearance-Consciousness | B19: 2 | D19: 7 | E19: 9
A20: Assertiveness | B20: 14 | D20: 32 | E20: 46
A21: Attention to Emotions | B21: 5 | D21: 5 | E21: 10
A22: Attractiveness | B22: 5 | D22: 5 | E22: 10
... A24: Belligerence | B24: 5 | D24: 5 | E24: 10
A25: Bravery/Courage/Valor | B25: 4 | C25: 1 | D25: 6 | E25: 11
A26: Callousness | B26: 1 | D26: 10 | E26: 11
A27: Calmness | B27: 24 | D27: 18 | E27: 42
A28: Capacity for Love | B28: 3 | C28: 1 | D28: 6 | E28: 10
A29: Cautiousness | B29: 10 | D29: 8 | E29: 18
A30: Cheerfulness | B30: 2 | D30: 8 | E30: 10
A31: Cognitive Problems | B31: 2 | D31: 6 | E31: 8
A32: Cognitive-Failures | B32: 4 | D32: 6 | E32: 10
A33: Compassion | B33: 12 | D33: 8 | E33: 20
A34: Competence | B34: 15 | D34: 18 | E34: 33
A35: Complexity | B35: 8 | D35: 10 | E35: 18
A36: Comprehension | B36: 6 | D36: 9 | E36: 15
A37: Conformity/Dependence/Need for approval | B37: 7 | D37: 21 | E37: 28
A38: Conscientiousness | B38: 24 | D38: 23 | E38: 47
A39: Conservatism | B39: 10 | D39: 14 | E39: 24
A40: Construction/Mechanical Interests | D40: 10 | E40: 10
A41: Cool-headedness | B41: 14 | D41: 2 | E41: 16
A42: Cooperation | B42: 25 | D42: 6 | E42: 31
A43: Creativity/Originality | B43: 15 | C43: 2 | D43: 39 | E43: 56
A44: Culture | B44: 5 | D44: 11 | E44: 16
A45: Curiosity | B45: 4 | D45: 18 | E45: 22
A46: Deliberateness | B46: 6 | D46: 4 | E46: 10
A47: Depression | B47: 8 | D47: 29 | E47: 37
A48: Depth | B48: 7 | D48: 12 | E48: 19
A49: Diligence | B49: 5 | D49: 5 | E49: 10
A50: Disorderliness | B50: 6 | D50: 4 | E50: 10
A51: Disparagement | D51: 4 | E51: 4
A52: Dissociation | D52: 31 | E52: 31
A53: Distrust | B53: 5 | D53: 10 | E53: 15
A54: Docility | B54: 2 | D54: 6 | E54: 8
A55: Dominance | B55: 5 | D55: 25 | E55: 30
A56: Dutifulness | B56: 26 | D56: 19 | E56: 45
A57: Efficiency | B57: 6 | D57: 5 | E57: 11
A58: Emotional Detachment | B58: 2 | D58: 5 | E58: 7
A59: Emotional Stability | B59: 19 | D59: 9 | E59: 28
A60: Emotionality | B60: 8 | D60: 12 | E60: 20
A61: Emotion-based Decision-making | B61: 4 | D61: 5 | E61: 9
A62: Empathy | B62: 15 | D62: 26 | E62: 41
A63: Equity/Fairness | B63: 7 | C63: 3 | D63: 12 | E63: 22
A64: Excitement-seeking | B64: 4 | D64: 12 | E64: 16
A65: Exhibitionism | B65: 7 | D65: 11 | E65: 18
A66: Expressiveness | B66: 5 | D66: 5 | E66: 10
A67: Extravagance | B67: 2 | D67: 2 | E67: 4
A68: Extraversion | B68: 20 | D68: 18 | E68: 38
A69: Fantasy Proneness | D69: 6 | E69: 6
A70: Fearfulness | B70: 5 | D70: 5 | E70: 10
A71: Femininity | B71: 2 | D71: 6 | E71: 8
A72: Flexibility | B72: 8 | D72: 2 | E72: 10
A73: Forcefulness | B73: 6 | D73: 4 | E73: 10
A74: Forgiveness/Mercy | B74: 11 | C74: 1 | D74: 16 | E74: 28
A75: Friendliness | B75: 14 | D75: 15 | E75: 29
A76: Gentleness | B76: 6 | D76: 4 | E76: 10
A77: Good Nature | B77: 9 | D77: 1 | E77: 10
A78: Grandiosity | D78: 7 | E78: 7
A79: Gratitude | B79: 2 | C79: 2 | D79: 6 | E79: 10
A80: Greed Avoidance | B80: 8 | D80: 2 | E80: 10
A81: Gregariousness | B81: 23 | D81: 24 | E81: 47
A82: Happiness | B82: 14 | D82: 10 | E82: 24
A83: Harm-Avoidance | B83: 7 | D83: 3 | E83: 10
A84: Health Anxiety | B84: 1 | D84: 6 | E84: 7
A85: Honesty/Integrity/Authenticity | B85: 4 | C85: 3 | D85: 5 | E85: 12
A86: Hope/Optimism | B86: 19 | C86: 1 | D86: 17 | E86: 37
A87: Hostile Aggression | D87: 8 | E87: 8
A88: Humor/Playfulness | B88: 4 | C88: 1 | D88: 20 | E88: 25
A89: Hypomanic Exhibitionism | B89: 3 | D89: 9 | E89: 12
A90: Hypomanic Mood Intensity | B90: 4 | D90: 8 | E90: 12
A91: Imagination | B91: 10 | D91: 18 | E91: 28
A92: Immoderation | B92: 5 | D92: 5 | E92: 10
A93: Imperturbability | B93: 7 | D93: 2 | E93: 9
A94: Impression-Management | B94: 10 | D94: 10 | E94: 20
A95: Impulse-Control | B95: 17 | D95: 10 | E95: 27
A96: Independence | B96: 6 | D96: 4 | E96: 10
A97: Industriousness/Perseverance/Persistence | B97: 14 | C97: 2 | D97: 21 | E97: 37
A98: Ingenuity | B98: 4 | D98: 8 | E98: 12
A99: Initiative | B99: 4 | D99: 6 | E99: 10
A100: Inquisitiveness | B100: 4 | D100: 6 | E100: 10
A101: Insight | B101: 5 | D101: 5 | E101: 10
A102: Intellect | B102: 18 | D102: 32 | E102: 50
A103: Intellectual Openness | B103: 13 | D103: 17 | E103: 30
...

Sheet data_nodupes
A1: instrument | B1: alpha | C1: key | D1: text | E1: label
A2: 16PF | B2: 0.78 | C2: 1 | D2: Act wild and crazy. | E2: Gregariousness
A3: 16PF | B3: 0.8 | C3: 1 | D3: Am afraid that I will do the wrong thing. | E3: Anxiety
A4: 16PF | B4: 0.76 | C4: 1 | D4: Am annoyed by others' mistakes. | E4: Emotionality
A5: 16PF | B5: 0.85 | C5: -1 | D5: Am easily discouraged. | E5: Emotional Stability
A6: 16PF | B6: 0.8 | C6: 1 | D6: Am easily hurt. | E6: Anxiety
A7: 16PF | B7: 0.76 | C7: 1 | D7: Am easily put out. | E7: Emotionality
A8: 16PF | B8: 0.81 | C8: 1 | D8: Am exacting in my work. | E8: Orderliness
A9: 16PF | B9: 0.86 | C9: 1 | D9: Am hard to get to know. | E9: Reserve
A10: 16PF | B10: 0.81 | C10: 1 | D10: Am not afraid of providing criticism. | E10: Dominance
A11: 16PF | B11: 0.81 | C11: 1 | D11: Am not afraid of providing criticism. | E11: Assertiveness
A12: 16PF | B12: 0.81 | C12: -1 | D12: Am not bothered by disorder. | E12: Orderliness
A13: 16PF | B13: 0.81 | C13: -1 | D13: Am not bothered by messy people. | E13: Orderliness
... A920: AB5C | B920: 0.71 | C920: 1 | D920: Wouldn't harm a fly. | E920: Nurturance
A921: Barchard2001 | B921: 0.59,0.63 | C921: -1 | D921: Am calm even in tense situations. | E921: Responsive Distress
A922: Barchard2001 | B922: 0.64,0.80 | C922: 1 | D922: Am concerned about others. | E922: Empathy
A923: Barchard2001 | B923: 0.59,0.63 | C923: 1 | D923: Am deeply moved by others' misfortunes. | E923: Responsive Distress
A924: Barchard2001 | B924: 0.59,0.63 | C924: 1 | D924: Am easily moved to tears. | E924: Responsive Distress
A925: Barchard2001 | B925: 0.59,0.63 | C925: -1 | D925: Am not easily disturbed by events. | E925: Responsive Distress
A926: Barchard2001 | B926: 0.81,0.83 | C926: -1 | D926: Am not in touch with my feelings. | E926: Attention to Emotions
A927: Barchard2001 | B927: 0.73,0.70 | C927: 1 | D927: Am strongly influenced by the good moods of others. | E927: Responsive Joy
A928: Barchard2001 | B928: 0.73,0.70 | C928: -1 | D928: Am unaffected by other people's happiness. | E928: Responsive Joy
A929: Barchard2001 | B929: 0.59,0.63 | C929: -1 | D929: Am unaffected by the suffering of others. | E929: Responsive Distress
A930: Barchard2001 | B930: 0.59,0.63 | C930: 1 | D930: Am upset by the misfortunes of strangers. | E930: Responsive Distress
A931: Barchard2001 | B931: 0.81,0.83 | C931: 1 | D931: Am usually aware of the way that I'm feeling. | E931: Attention to Emotions
A932: Barchard2001 | B932: 0.73,0.67 | C932: 1 | D932: Base my goals in life on inspiration, rather than logic. | E932: Emotion-based Decision-making
... A988: Barchard2001 | B988: 0.59,0.63 | C988: 1 | D988: Would be upset if I saw an injured animal. | E988: Responsive Distress
A989: BFAS | B989: 0.81 | C989: 1 | D989: Always know what I am doing. | E989: Industriousness/Perseverance/Persistence
A990: BFAS | B990: 0.89 | C990: 1 | D990: Am a person whose moods go up and down easily. | E990: Neuroticism
A991: BFAS | B991: 0.89 | C991: 1 | D991: Am a person whose moods go up and down easily. | E991: Anger
A992: BFAS | B992: 0.89 | C992: 1 | D992: Am afraid of many things. | E992: Neuroticism
A993: BFAS | B993: 0.84 | C993: 1 | D993: Am afraid of many things. | E993: Anxiety
A994: BFAS | B994: 0.89 | C994: 1 | D994: Am easily discouraged. | E994: Neuroticism
A995: BFAS | B995: 0.84 | C995: 1 | D995: Am easily discouraged. | E995: Anxiety
A996: BFAS | B996: 0.81 | C996: -1 | D996: Am easily distracted. | E996: Industriousness/Perseverance/Persistence
A997: BFAS | B997: 0.89 | C997: 1 | D997: Am filled with doubts about things. | E997: Neuroticism
A998: BFAS | B998: 0.84 | C998: 1 | D998: Am filled with doubts about things. | E998: Anxiety
A999: BFAS | B999: 0.81 | C999: -1 | D999: Am hard to get to know. | E999: Vitality/Enthusiasm/Zest
A1000: BFAS | B1000: 0.84 | C1000: -1 | D1000: Am indifferent to the feelings of others. | E1000: Compassion
... A1290: Cacioppo1982 | B1290: 0.93 | C1290: -1 | D1290: Try to avoid complex people. | E1290: Need for Cognition
A1291: CAT-PD | B1291: 0.82,0.84 | C1291: 1 | D1291: Act without planning. | E1291: Non-Planfulness
A1292: CAT-PD | B1292: 0.85,0.83 | C1292: 1 | D1292: Am a cold-hearted person. | E1292: Callousness
A1293: CAT-PD | B1293: 0.82,0.84 | C1293: -1 | D1293: Am a firm believer in thinking things through. | E1293: Non-Planfulness
A1294: CAT-PD | B1294: 0.83,0.84 | C1294: -1 | D1294: Am a law-abiding citizen. | E1294: Norm Violation
A1295: CAT-PD | B1295: 0.86,0.82 | C1295: 1 | D1295: Am a strange person. | E1295: Peculiarity
A1296: CAT-PD | B1296: 0.82,0.85 | C1296: -1 | D1296: Am a very reliable person. | E1296: Irresponsibility
A1297: CAT-PD | B1297: 0.83,0.85 | C1297: 1 | D1297: Am a workaholic, with little time for fun or pleasure. | E1297: Workaholism
A1298: CAT-PD | B1298: 0.82,0.86 | C1298: -1 | D1298: Am able to describe my feelings easily. | E1298: Emotional Detachment
A1299: CAT-PD | B1299: 0.83,0.84 | C1299: 1 | D1299: Am able to read the minds of others. | E1299: Irrational Beliefs
A1300: CAT-PD | B1300: 0.84,0.84 | C1300: 1 | D1300: Am afraid that my life will be cut short by illness. | E1300: Health Anxiety
A1301: CAT-PD | B1301: 0.84,0.83 | C1301: 1 | D1301: Am always worried that my partner is going to leave me. | E1301: Relationship Insecurity
A1302: CAT-PD | B1302: 0.84,0.89 | C1302: -1 | D1302: Am an energetic person. | E1302: Anhedonia
... A1500: CAT-PD | B1500: 0.84,0.84 | C1500: 1 | D1500: Would do anything to get an adrenaline rush. | E1500: Risk-taking/Sensation-Seeking/Thrill-Seeking
A1501: Chapman1986 | B1501: 0.77 | C1501: 1 | D1501: Am a person whose moods go up and down easily. | E1501: Hypomanic Mood Intensity
A1502: Chapman1986 | B1502: 0.77 | C1502: 1 | D1502: Am considered to be kind of eccentric. | E1502: Hypomanic Mood Intensity
A1503: Chapman1986 | B1503: 0.81 | C1503: 1 | D1503: Am often so assertive or sociable that I surprise myself. | E1503: Hypomanic Exhibitionism
A1504: Chapman1986 | B1504: 0.77 | C1504: 1 | D1504: Am often so restless that it is impossible for me to sit still. | E1504: Hypomanic Mood Intensity
A1505: Chapman1986 | B1505: 0.81 | C1505: 1 | D1505: Am so good at controlling others that it sometimes scares me. | E1505: Hypomanic Exhibitionism
A1506: Chapman1986 | B1506: 0.77 | C1506: -1 | D1506: Am usually in an average sort of mood, not too high and not too low. | E1506: Hypomanic Mood Intensity
A1507: Chapman1986 | B1507: 0.81 | C1507: 1 | D1507: Can play many roles convincingly. | E1507: Hypomanic Exhibitionism
A1508: Chapman1986 | B1508: 0.77 | C1508: -1 | D1508: Can slow myself down when I want to. | E1508: Hypomanic Mood Intensity
A1509: Chapman1986 | B1509: 0.81 | C1509: 1 | D1509: Could be a success in many fields. | E1509: Hypomanic Exhibitionism
A1510: Chapman1986 | B1510: 0.77 | C1510: 1 | D1510: Feel emotions with extreme intensity. | E1510: Hypomanic Mood Intensity
A1511: Chapman1986 | B1511: 0.77 | C1511: 1 | D1511: Find that my thoughts are racing. | E1511: Hypomanic Mood Intensity
A1512: Chapman1986 | B1512: 0.77 | C1512: 1 | D1512: Get into moods where I feel very speeded up and irritable. | E1512: Hypomanic Mood Intensity
... A2439: HPI-HIC | B2439: 0.81 | C2439: -1 | D2439: Yell at people. | E2439: Cool-headedness
A2440: IPIP-IPC | B2440: . | C2440: 1 | D2440: Am a very private person | E2440: Introversion
A2441: IPIP-IPC | B2441: . | C2441: 1 | D2441: Am interested in people | E2441: Warmth
A2442: IPIP-IPC | B2442: . | C2442: 1 | D2442: Am not interested in other people’s problems. | E2442: Callousness
A2443: IPIP-IPC | B2443: . | C2443: 1 | D2443: Am quiet around strangers | E2443: Introversion
A2444: IPIP-IPC | B2444: . | C2444: 1 | D2444: Believe people should fend for themselves. | E2444: Callousness
A2445: IPIP-IPC | B2445: . | C2445: 1 | D2445: Contradict others | E2445: Disparagement
A2446: IPIP-IPC | B2446: . | C2446: 1 | D2446: Cut others to pieces. | E2446: Disparagement
A2447: IPIP-IPC | B2447: . | C2447: 1 | D2447: Demand attention | E2447: Dominance
A2448: IPIP-IPC | B2448: . | C2448: 1 | D2448: Demand to be the center of interest. | E2448: Dominance
A2449: IPIP-IPC | B2449: . | C2449: 1 | D2449: Dislike being the center of attention | E2449: Submissiveness
A2450: IPIP-IPC | B2450: . | C2450: 1 | D2450: Do most of the talking. | E2450: Dominance
A2451: IPIP-IPC | B2451: . | C2451: 1 | D2451: Don't fall for sob stories. | E2451: Callousness
... A2471: IPIP-IPC | B2471: . | C2471: 1 | D2471: Tolerate a lot from others. | E2471: Tolerance
A2472: JPI | B2472: 0.81 | C2472: 1 | D2472: Accomplish a lot of work. | E2472: Activity-Level
A2473: JPI | B2473: 0.78 | C2473: -1 | D2473: Am a very private person. | E2473: Sociability
A2474: JPI | B2474: 0.81 | C2474: 1 | D2474: Am always busy. | E2474: Activity-Level
A2475: JPI | B2475: 0.81 | C2475: 1 | D2475: Am always on the go. | E2475: Activity-Level
A2476: JPI | B2476: 0.8 | C2476: 1 | D2476: Am deeply moved by others' misfortunes. | E2476: Empathy
A2477: JPI | B2477: 0.87 | C2477: 1 | D2477: Am devoted to religion. | E2477: Traditionalism
A2478: JPI | B2478: 0.81 | C2478: -1 | D2478: Am easily discouraged. | E2478: Activity-Level
A2479: JPI | B2479: 0.8 | C2479: 1 | D2479: Am easily moved to tears. | E2479: Empathy
A2480: JPI | B2480: 0.87 | C2480: 1 | D2480: Am good at making impromptu speeches. | E2480: Social-confidence
A2481: JPI | B2481: 0.79 | C2481: 1 | D2481: Am interested in many things. | E2481: Intellectual-Breadth
A2482: JPI | B2482: 0.78 | C2482: 1 | D2482: Am interested in people. | E2482: Sociability
A2483: JPI | B2483: 0.71 | C2483: -1 | D2483: Am not concerned with making a good impression. | E2483: Conformity/Dependence/Need for approval
... A3806: VIA | B3806: 0.7 | C3806: 1 | D3806: Would never be described as arrogant. | E3806: Modesty/Humility

Sheet 資料範例
B3: 題庫主檔 | E3: 測卷主檔 | H3: 測卷明細檔
B4: ID | C4: TEXT | E4: ID | F4: TEXT | H4: ID | I4: 測卷ID | J4: 題庫ID
B5: 1 | C5: AAAAA | E5: 1 | F5: AA | H5: 1 | I5: 1 | J5: 10
B6: 2 | C6: BBBBB | E6: 2 | F6: BB | H6: =H5+1 -> 2 | I6: 1 | J6: 20
B7: 3 | C7: CCCCC | E7: 3 | F7: CC | H7: =H6+1 -> 3 | I7: 1 | J7: 30
B8: …. | C8: …. | H8: =H7+1 -> 4 | I8: 1 | J8: 40
B9: 3800 | H9: =H8+1 -> 5 | I9: 1 | J9: 50
H10: =H9+1 -> 6 | I10: 2 | J10: 100
H11: =H10+1 -> 7 | I11: 2 | J11: 110
H12: =H11+1 -> 8 | I12: 2 | J12: 120
H13: =H12+1 -> 9 | I13: 2 | J13: 130
H14: =H13+1 -> 10 | I14: 2 | J14: 140
H15: =H14+1 -> 11 | I15: 2 | J15: 150
H16: =H15+1 -> 12 | I16: 3 | J16: 1010
H17: =H16+1 -> 13 | I17: 3 | J17: 1020
H18: =H17+1 -> 14 | I18: 3 | J18: 1030
H19: =H18+1 -> 15 | I19: 3 | J19: 1040
H20: =H19+1 -> 16 | I20: 3 | J20: 1050
B23: 受測主檔 | H23: 受測作答明細檔
B24: ID | C24: 測卷ID | D24: 受測者姓名 | H24: ID | I24: 受測ID | J24: 測卷明細ID | K24: 作答
B25: 1 | C25: 1 | D25: AAA | H25: 1 | I25: 1 | J25: 1 | K25: 1…5
B26: 2 | C26: 2 | D26: AAA | H26: =H25+1 -> 2 | I26: 1 | J26: =J25+1 -> 2 | K26: 1…5
B27: 3 | C27: 1 | D27: BBB | H27: =H26+1 -> 3 | I27: 1 | J27: =J26+1 -> 3 | K27: 1…5
B28: 4 | C28: 2 | D28: CCC | H28: =H27+1 -> 4 | I28: 1 | J28: =J27+1 -> 4 | K28: 1…5
B29: 5 | C29: 3 | D29: DDD | H29: =H28+1 -> 5 | I29: 1 | J29: =J28+1 -> 5 | K29: 1…5
B30: 6 | C30: 3 | D30: CCC | H30: =H29+1 -> 6 | I30: 2 | J30: 6 | K30: 1…5
H31: =H30+1 -> 7 | I31: =I30 -> 2 | J31: 7 | K31: 1…5
H32: =H31+1 -> 8 | I32: =I31 -> 2 | J32: 8 | K32: 1…5
H33: =H32+1 -> 9 | I33: =I32 -> 2 | J33: 9 | K33: 1…5
H34: =H33+1 -> 10 | I34: =I33 -> 2 | J34: 10 | K34: 1…5
H35: =H34+1 -> 11 | I35: =I34 -> 2 | J35: 11 | K35: 1…5
H36: =H35+1 -> 12 | I36: 3 | J36: 1 | K36: 1…5
H37: =H36+1 -> 13 | I37: 3 | J37: 2 | K37: 1…5
H38: =H37+1 -> 14 | I38: 3 | J38: 3 | K38: 1…5
H39: =H38+1 -> 15 | I39: 3 | J39: 4 | K39: 1…5
H40: =H39+1 -> 16 | I40: 3 | J40: 5 | K40: 1…5

Sheet IPIP3320
A1: 題目 | B1: 編號? | E1: CHK
A2: Abuse people's confidences. | B2: H1131 | E2: =_xlfn.XLOOKUP(A2,data_nodupes!D:D,data_nodupes!D:D) -> #N/A
A3: Accept apologies easily. | B3: H133 | E3: =_xlfn.XLOOKUP(A3,data_nodupes!D:D,data_nodupes!D:D) -> Accept apologies easily.
A4: Accept challenging tasks. | B4: H515 | E4: =_xlfn.XLOOKUP(A4,data_nodupes!D:D,data_nodupes!D:D) -> Accept challenging tasks.
A5: Accept little from others. | B5: H615 | E5: =_xlfn.XLOOKUP(A5,data_nodupes!D:D,data_nodupes!D:D) -> #N/A
A6: Accept others' weaknesses. | B6: H139 | E6: =_xlfn.XLOOKUP(A6,data_nodupes!D:D,data_nodupes!D:D) -> Accept others' weaknesses.
A7: Accept people as they are. | B7: H106 | E7: =_xlfn.XLOOKUP(A7,data_nodupes!D:D,data_nodupes!D:D) -> Accept people as they are.
A8: Accept the consequences of my actions. | B8: H266 | E8: =_xlfn.XLOOKUP(A8,data_nodupes!D:D,data_nodupes!D:D) -> #N/A
A9: Accept the first thing that comes along. | B9: H1384 | E9: =_xlfn.XLOOKUP(A9,data_nodupes!D:D,data_nodupes!D:D) -> #N/A
A10: Accept what others say. | B10: H962 | E10: =_xlfn.XLOOKUP(A10,data_nodupes!D:D,data_nodupes!D:D) -> #N/A
A11: Accomplish a lot of work. | B11: H554 | E11: =_xlfn.XLOOKUP(A11,data_nodupes!D:D,data_nodupes!D:D) -> Accomplish a lot of work.
A12: Accomplish my work on time. | B12: H230 | E12: =_xlfn.XLOOKUP(A12,data_nodupes!D:D,data_nodupes!D:D) -> Accomplish my work on time.
A13: Acknowledge others' accomplishments. | B13: H152 | E13: =_xlfn.XLOOKUP(A13,data_nodupes!D:D,data_nodupes!D:D) -> Acknowledge others' accomplishments.
... A3321: Yell at people. | B3321: H809 | E3321: =_xlfn.XLOOKUP(A3321,data_nodupes!D:D,data_nodupes!D:D) -> Yell at people.
